{"v":"5.9.0","fr":30,"ip":0,"op":181,"w":1488,"h":1080,"nm":"Comp 1","ddd":0,"assets":[{"id":"comp_0","nm":"Tingu in litter box","fr":30,"layers":[{"ddd":0,"ind":1,"ty":0,"nm":"Left eye","refId":"comp_1","sr":1,"ks":{"o":{"a":0,"k":100,"ix":11},"r":{"a":0,"k":0,"ix":10},"p":{"a":0,"k":[628.278,288.444,0],"ix":2,"l":2},"a":{"a":0,"k":[417.389,303.556,0],"ix":1,"l":2},"s":{"a":0,"k":[100,100,100],"ix":6,"l":2}},"ao":0,"w":1489,"h":1080,"ip":0,"op":181,"st":0,"bm":0},{"ddd":0,"ind":4,"ty":0,"nm":"Left eye","refId":"comp_1","sr":1,"ks":{"o":{"a":0,"k":100,"ix":11},"r":{"a":0,"k":0,"ix":10},"p":{"a":0,"k":[417.389,288.444,0],"ix":2,"l":2},"a":{"a":0,"k":[417.389,303.556,0],"ix":1,"l":2},"s":{"a":0,"k":[100,100,100],"ix":6,"l":2}},"ao":0,"w":1489,"h":1080,"ip":0,"op":181,"st":0,"bm":0},{"ddd":0,"ind":6,"ty":0,"nm":"Fly","refId":"comp_2","sr":1,"ks":{"o":{"a":0,"k":100,"ix":11},"r":{"a":0,"k":-42,"ix":10},"p":{"a":1,"k":[{"i":{"x":0.833,"y":0.833},"o":{"x":0.167,"y":0.167},"t":0,"s":[1319,375.271,0],"to":[0,0,0],"ti":[0,0,0]},{"i":{"x":0.833,"y":0.833},"o":{"x":0.167,"y":0.167},"t":30,"s":[1335,376.271,0],"to":[0,0,0],"ti":[0,0,0]},{"i":{"x":0.833,"y":0.833},"o":{"x":0.167,"y":0.167},"t":61,"s":[1346,392.271,0],"to":[0,0,0],"ti":[0,0,0]},{"i":{"x":0.833,"y":0.833},"o":{"x":0.167,"y":0.167},"t":90,"s":[1359,368.271,0],"to":[0,0,0],"ti":[0,0,0]},{"i":{"x":0.833,"y":0.833},"o":{"x":0.167,"y":0.167},"t":120,"s":[1347,357.271,0],"to":[0,0,0],"ti":[0,0,0]},{"i":{"x":0.833,"y":0.833},"o":{"x":0.167,"y":0.167},"t":150,"s":[1335,351.271,0],"to":[0,0,0],"ti":[0,0,0]},{"t":180,"s":[1319,375.271,0]}],"ix":2,"l":2},"a":{"a":0,"k":[1196.194,276.387,0],"ix":1,"l":2},"s":{"a":0,"k":[86,86,100],"ix":6,"l":2}},"ao":0,"w":1489,"h":1080,"ip":0,"op":210,"st":0,"bm":0},{"ddd":0,"ind":7,"ty":0,"nm":"Fly","refId":"comp_2","sr":1,"ks":{"o":{"a":0,"k":100,"ix":11},"r":{"a":0,"k":33,"ix":10},"p":{"a":1,"k":[{"i":{"x":0.833,"y":0.833},"o":{"x":0.167,"y":0.167},"t":0,"s":[1224,324.271,0],"to":[0,0,0],"ti":[0,0,0]},{"i":{"x":0.833,"y":0.833},"o":{"x":0.167,"y":0.167},"t":30,"s":[1240,300.271,0],"to":[0,0,0],"ti":[0,0,0]},{"i":{"x":0.833,"y":0.833},"o":{"x":0.167,"y":0.167},"t":60,"s":[1252,306.271,0],"to":[0,0,0],"ti":[0,0,0]},{"i":{"x":0.833,"y":0.833},"o":{"x":0.167,"y":0.167},"t":90,"s":[1264,317.271,0],"to":[0,0,0],"ti":[0,0,0]},{"i":{"x":0.833,"y":0.833},"o":{"x":0.167,"y":0.167},"t":119,"s":[1251,341.271,0],"to":[0,0,0],"ti":[0,0,0]},{"i":{"x":0.833,"y":0.833},"o":{"x":0.167,"y":0.167},"t":150,"s":[1240,325.271,0],"to":[0,0,0],"ti":[0,0,0]},{"t":180,"s":[1224,324.271,0]}],"ix":2,"l":2},"a":{"a":0,"k":[1196.194,276.387,0],"ix":1,"l":2},"s":{"a":0,"k":[-86,86,100],"ix":6,"l":2}},"ao":0,"w":1489,"h":1080,"ip":0,"op":210,"st":0,"bm":0},{"ddd":0,"ind":8,"ty":4,"nm":"wave Outlines 6","sr":1,"ks":{"o":{"a":0,"k":100,"ix":11},"r":{"a":0,"k":0,"ix":10},"p":{"a":0,"k":[1344.056,530.275,0],"ix":2,"l":2},"a":{"a":0,"k":[113.922,134.372,0],"ix":1,"l":2},"s":{"a":0,"k":[100,100,100],"ix":6,"l":2}},"ao":0,"shapes":[{"ty":"gr","it":[{"ind":0,"ty":"sh","ix":1,"ks":{"a":0,"k":{"i":[[0,0],[-8.784,-43.199],[-6.069,-32.461],[0,0]],"o":[[0,0],[8.785,43.202],[7.82,41.836],[0,0]],"v":[[0.481,-112.546],[-34.988,-32.059],[35.952,50.703],[0.481,112.546]],"c":false},"ix":2},"nm":"Path 1","mn":"ADBE Vector Shape - Group","hd":false},{"ty":"st","c":{"a":0,"k":[0.764705942191,0.733333333333,0.776470648074,1],"ix":3},"o":{"a":0,"k":100,"ix":4},"w":{"a":0,"k":21.827,"ix":5},"lc":2,"lj":1,"ml":4,"bm":0,"nm":"Stroke 1","mn":"ADBE Vector Graphic - Stroke","hd":false},{"ty":"tr","p":{"a":0,"k":[65.599,134.373],"ix":2},"a":{"a":0,"k":[0,0],"ix":1},"s":{"a":0,"k":[100,100],"ix":3},"r":{"a":0,"k":0,"ix":6},"o":{"a":0,"k":100,"ix":7},"sk":{"a":0,"k":0,"ix":4},"sa":{"a":0,"k":0,"ix":5},"nm":"Transform"}],"nm":"Group 2","np":2,"cix":2,"bm":0,"ix":1,"mn":"ADBE Vector Group","hd":false},{"ty":"tm","s":{"a":1,"k":[{"i":{"x":[0.667],"y":[1]},"o":{"x":[0.333],"y":[0]},"t":150,"s":[88]},{"t":165,"s":[0]}],"ix":1},"e":{"a":1,"k":[{"i":{"x":[0.667],"y":[1]},"o":{"x":[0.333],"y":[0]},"t":165,"s":[100]},{"t":180,"s":[0]}],"ix":2},"o":{"a":0,"k":0,"ix":3},"m":1,"ix":2,"nm":"Trim Paths 1","mn":"ADBE Vector Filter - Trim","hd":false}],"ip":150,"op":181,"st":150,"bm":0},{"ddd":0,"ind":9,"ty":4,"nm":"wave Outlines 4","sr":1,"ks":{"o":{"a":0,"k":100,"ix":11},"r":{"a":0,"k":0,"ix":10},"p":{"a":0,"k":[1344.056,530.275,0],"ix":2,"l":2},"a":{"a":0,"k":[113.922,134.372,0],"ix":1,"l":2},"s":{"a":0,"k":[100,100,100],"ix":6,"l":2}},"ao":0,"shapes":[{"ty":"gr","it":[{"ind":0,"ty":"sh","ix":1,"ks":{"a":0,"k":{"i":[[0,0],[-8.784,-43.199],[-6.069,-32.461],[0,0]],"o":[[0,0],[8.785,43.202],[7.82,41.836],[0,0]],"v":[[0.481,-112.546],[-34.988,-32.059],[35.952,50.703],[0.481,112.546]],"c":false},"ix":2},"nm":"Path 1","mn":"ADBE Vector Shape - Group","hd":false},{"ty":"st","c":{"a":0,"k":[0.764705942191,0.733333333333,0.776470648074,1],"ix":3},"o":{"a":0,"k":100,"ix":4},"w":{"a":0,"k":21.827,"ix":5},"lc":2,"lj":1,"ml":4,"bm":0,"nm":"Stroke 1","mn":"ADBE Vector Graphic - Stroke","hd":false},{"ty":"tr","p":{"a":0,"k":[65.599,134.373],"ix":2},"a":{"a":0,"k":[0,0],"ix":1},"s":{"a":0,"k":[100,100],"ix":3},"r":{"a":0,"k":0,"ix":6},"o":{"a":0,"k":100,"ix":7},"sk":{"a":0,"k":0,"ix":4},"sa":{"a":0,"k":0,"ix":5},"nm":"Transform"}],"nm":"Group 2","np":2,"cix":2,"bm":0,"ix":1,"mn":"ADBE Vector Group","hd":false},{"ty":"tm","s":{"a":1,"k":[{"i":{"x":[0.667],"y":[1]},"o":{"x":[0.333],"y":[0]},"t":84,"s":[88]},{"t":99,"s":[0]}],"ix":1},"e":{"a":1,"k":[{"i":{"x":[0.667],"y":[1]},"o":{"x":[0.333],"y":[0]},"t":99,"s":[100]},{"t":114,"s":[0]}],"ix":2},"o":{"a":0,"k":0,"ix":3},"m":1,"ix":2,"nm":"Trim Paths 1","mn":"ADBE Vector Filter - Trim","hd":false}],"ip":84,"op":115,"st":84,"bm":0},{"ddd":0,"ind":10,"ty":4,"nm":"wave Outlines 2","sr":1,"ks":{"o":{"a":0,"k":100,"ix":11},"r":{"a":0,"k":0,"ix":10},"p":{"a":0,"k":[1344.056,530.275,0],"ix":2,"l":2},"a":{"a":0,"k":[113.922,134.372,0],"ix":1,"l":2},"s":{"a":0,"k":[100,100,100],"ix":6,"l":2}},"ao":0,"shapes":[{"ty":"gr","it":[{"ind":0,"ty":"sh","ix":1,"ks":{"a":0,"k":{"i":[[0,0],[-8.784,-43.199],[-6.069,-32.461],[0,0]],"o":[[0,0],[8.785,43.202],[7.82,41.836],[0,0]],"v":[[0.481,-112.546],[-34.988,-32.059],[35.952,50.703],[0.481,112.546]],"c":false},"ix":2},"nm":"Path 1","mn":"ADBE Vector Shape - Group","hd":false},{"ty":"st","c":{"a":0,"k":[0.764705942191,0.733333333333,0.776470648074,1],"ix":3},"o":{"a":0,"k":100,"ix":4},"w":{"a":0,"k":21.827,"ix":5},"lc":2,"lj":1,"ml":4,"bm":0,"nm":"Stroke 1","mn":"ADBE Vector Graphic - Stroke","hd":false},{"ty":"tr","p":{"a":0,"k":[65.599,134.373],"ix":2},"a":{"a":0,"k":[0,0],"ix":1},"s":{"a":0,"k":[100,100],"ix":3},"r":{"a":0,"k":0,"ix":6},"o":{"a":0,"k":100,"ix":7},"sk":{"a":0,"k":0,"ix":4},"sa":{"a":0,"k":0,"ix":5},"nm":"Transform"}],"nm":"Group 2","np":2,"cix":2,"bm":0,"ix":1,"mn":"ADBE Vector Group","hd":false},{"ty":"tm","s":{"a":1,"k":[{"i":{"x":[0.667],"y":[1]},"o":{"x":[0.333],"y":[0]},"t":10,"s":[88]},{"t":25,"s":[0]}],"ix":1},"e":{"a":1,"k":[{"i":{"x":[0.667],"y":[1]},"o":{"x":[0.333],"y":[0]},"t":25,"s":[100]},{"t":40,"s":[0]}],"ix":2},"o":{"a":0,"k":0,"ix":3},"m":1,"ix":2,"nm":"Trim Paths 1","mn":"ADBE Vector Filter - Trim","hd":false}],"ip":10,"op":41,"st":10,"bm":0},{"ddd":0,"ind":11,"ty":4,"nm":"wave Outlines 5","sr":1,"ks":{"o":{"a":0,"k":100,"ix":11},"r":{"a":0,"k":0,"ix":10},"p":{"a":0,"k":[1233.088,530.275,0],"ix":2,"l":2},"a":{"a":0,"k":[113.922,134.372,0],"ix":1,"l":2},"s":{"a":0,"k":[100,100,100],"ix":6,"l":2}},"ao":0,"shapes":[{"ty":"gr","it":[{"ind":0,"ty":"sh","ix":1,"ks":{"a":0,"k":{"i":[[0,0],[-8.784,-43.199],[-6.069,-32.461],[0,0]],"o":[[0,0],[8.785,43.202],[7.82,41.836],[0,0]],"v":[[0.481,-112.546],[-34.988,-32.059],[35.952,50.703],[0.481,112.546]],"c":false},"ix":2},"nm":"Path 1","mn":"ADBE Vector Shape - Group","hd":false},{"ty":"st","c":{"a":0,"k":[0.764705942191,0.733333333333,0.776470648074,1],"ix":3},"o":{"a":0,"k":100,"ix":4},"w":{"a":0,"k":21.827,"ix":5},"lc":2,"lj":1,"ml":4,"bm":0,"nm":"Stroke 1","mn":"ADBE Vector Graphic - Stroke","hd":false},{"ty":"tr","p":{"a":0,"k":[65.599,134.373],"ix":2},"a":{"a":0,"k":[0,0],"ix":1},"s":{"a":0,"k":[100,100],"ix":3},"r":{"a":0,"k":0,"ix":6},"o":{"a":0,"k":100,"ix":7},"sk":{"a":0,"k":0,"ix":4},"sa":{"a":0,"k":0,"ix":5},"nm":"Transform"}],"nm":"Group 2","np":2,"cix":2,"bm":0,"ix":1,"mn":"ADBE Vector Group","hd":false},{"ty":"tm","s":{"a":1,"k":[{"i":{"x":[0.667],"y":[1]},"o":{"x":[0.333],"y":[0]},"t":140,"s":[88]},{"t":155,"s":[0]}],"ix":1},"e":{"a":1,"k":[{"i":{"x":[0.667],"y":[1]},"o":{"x":[0.333],"y":[0]},"t":155,"s":[100]},{"t":170,"s":[0]}],"ix":2},"o":{"a":0,"k":0,"ix":3},"m":1,"ix":2,"nm":"Trim Paths 1","mn":"ADBE Vector Filter - Trim","hd":false}],"ip":140,"op":171,"st":140,"bm":0},{"ddd":0,"ind":12,"ty":4,"nm":"wave Outlines 3","sr":1,"ks":{"o":{"a":0,"k":100,"ix":11},"r":{"a":0,"k":0,"ix":10},"p":{"a":0,"k":[1233.088,530.275,0],"ix":2,"l":2},"a":{"a":0,"k":[113.922,134.372,0],"ix":1,"l":2},"s":{"a":0,"k":[100,100,100],"ix":6,"l":2}},"ao":0,"shapes":[{"ty":"gr","it":[{"ind":0,"ty":"sh","ix":1,"ks":{"a":0,"k":{"i":[[0,0],[-8.784,-43.199],[-6.069,-32.461],[0,0]],"o":[[0,0],[8.785,43.202],[7.82,41.836],[0,0]],"v":[[0.481,-112.546],[-34.988,-32.059],[35.952,50.703],[0.481,112.546]],"c":false},"ix":2},"nm":"Path 1","mn":"ADBE Vector Shape - Group","hd":false},{"ty":"st","c":{"a":0,"k":[0.764705942191,0.733333333333,0.776470648074,1],"ix":3},"o":{"a":0,"k":100,"ix":4},"w":{"a":0,"k":21.827,"ix":5},"lc":2,"lj":1,"ml":4,"bm":0,"nm":"Stroke 1","mn":"ADBE Vector Graphic - Stroke","hd":false},{"ty":"tr","p":{"a":0,"k":[65.599,134.373],"ix":2},"a":{"a":0,"k":[0,0],"ix":1},"s":{"a":0,"k":[100,100],"ix":3},"r":{"a":0,"k":0,"ix":6},"o":{"a":0,"k":100,"ix":7},"sk":{"a":0,"k":0,"ix":4},"sa":{"a":0,"k":0,"ix":5},"nm":"Transform"}],"nm":"Group 2","np":2,"cix":2,"bm":0,"ix":1,"mn":"ADBE Vector Group","hd":false},{"ty":"tm","s":{"a":1,"k":[{"i":{"x":[0.667],"y":[1]},"o":{"x":[0.333],"y":[0]},"t":74,"s":[88]},{"t":89,"s":[0]}],"ix":1},"e":{"a":1,"k":[{"i":{"x":[0.667],"y":[1]},"o":{"x":[0.333],"y":[0]},"t":89,"s":[100]},{"t":104,"s":[0]}],"ix":2},"o":{"a":0,"k":0,"ix":3},"m":1,"ix":2,"nm":"Trim Paths 1","mn":"ADBE Vector Filter - Trim","hd":false}],"ip":74,"op":105,"st":74,"bm":0},{"ddd":0,"ind":13,"ty":4,"nm":"wave Outlines","sr":1,"ks":{"o":{"a":0,"k":100,"ix":11},"r":{"a":0,"k":0,"ix":10},"p":{"a":0,"k":[1233.088,530.275,0],"ix":2,"l":2},"a":{"a":0,"k":[113.922,134.372,0],"ix":1,"l":2},"s":{"a":0,"k":[100,100,100],"ix":6,"l":2}},"ao":0,"shapes":[{"ty":"gr","it":[{"ind":0,"ty":"sh","ix":1,"ks":{"a":0,"k":{"i":[[0,0],[-8.784,-43.199],[-6.069,-32.461],[0,0]],"o":[[0,0],[8.785,43.202],[7.82,41.836],[0,0]],"v":[[0.481,-112.546],[-34.988,-32.059],[35.952,50.703],[0.481,112.546]],"c":false},"ix":2},"nm":"Path 1","mn":"ADBE Vector Shape - Group","hd":false},{"ty":"st","c":{"a":0,"k":[0.764705942191,0.733333333333,0.776470648074,1],"ix":3},"o":{"a":0,"k":100,"ix":4},"w":{"a":0,"k":21.827,"ix":5},"lc":2,"lj":1,"ml":4,"bm":0,"nm":"Stroke 1","mn":"ADBE Vector Graphic - Stroke","hd":false},{"ty":"tr","p":{"a":0,"k":[65.599,134.373],"ix":2},"a":{"a":0,"k":[0,0],"ix":1},"s":{"a":0,"k":[100,100],"ix":3},"r":{"a":0,"k":0,"ix":6},"o":{"a":0,"k":100,"ix":7},"sk":{"a":0,"k":0,"ix":4},"sa":{"a":0,"k":0,"ix":5},"nm":"Transform"}],"nm":"Group 2","np":2,"cix":2,"bm":0,"ix":1,"mn":"ADBE Vector Group","hd":false},{"ty":"tm","s":{"a":1,"k":[{"i":{"x":[0.667],"y":[1]},"o":{"x":[0.333],"y":[0]},"t":0,"s":[88]},{"t":15,"s":[0]}],"ix":1},"e":{"a":1,"k":[{"i":{"x":[0.667],"y":[1]},"o":{"x":[0.333],"y":[0]},"t":15,"s":[100]},{"t":30,"s":[0]}],"ix":2},"o":{"a":0,"k":0,"ix":3},"m":1,"ix":2,"nm":"Trim Paths 1","mn":"ADBE Vector Filter - Trim","hd":false}],"ip":0,"op":31,"st":0,"bm":0},{"ddd":0,"ind":14,"ty":4,"nm":"tingu Outlines","sr":1,"ks":{"o":{"a":0,"k":100,"ix":11},"r":{"a":0,"k":0,"ix":10},"p":{"a":0,"k":[739.371,545.769,0],"ix":2,"l":2},"a":{"a":0,"k":[689.369,501.758,0],"ix":1,"l":2},"s":{"a":0,"k":[100,100,100],"ix":6,"l":2}},"ao":0,"shapes":[{"ty":"gr","it":[{"ind":0,"ty":"sh","ix":1,"ks":{"a":0,"k":{"i":[[13.212,0],[0,0],[0,13.213],[0,0],[-13.212,0],[0,0],[0,-13.212],[0,0]],"o":[[0,0],[-13.212,0],[0,0],[0,-13.212],[0,0],[13.212,0],[0,0],[0,13.213]],"v":[[56.892,23.932],[-56.892,23.932],[-80.815,0.009],[-80.815,-0.009],[-56.892,-23.932],[56.892,-23.932],[80.815,-0.009],[80.815,0.009]],"c":true},"ix":2},"nm":"Path 1","mn":"ADBE Vector Shape - Group","hd":false},{"ty":"fl","c":{"a":0,"k":[0.023529413635,0.423529441684,0.745098039216,1],"ix":4},"o":{"a":0,"k":100,"ix":5},"r":1,"bm":0,"nm":"Fill 1","mn":"ADBE Vector Graphic - Fill","hd":false},{"ty":"tr","p":{"a":0,"k":[397.008,897.719],"ix":2},"a":{"a":0,"k":[0,0],"ix":1},"s":{"a":0,"k":[100,100],"ix":3},"r":{"a":0,"k":0,"ix":6},"o":{"a":0,"k":100,"ix":7},"sk":{"a":0,"k":0,"ix":4},"sa":{"a":0,"k":0,"ix":5},"nm":"Transform"}],"nm":"Group 1","np":2,"cix":2,"bm":0,"ix":1,"mn":"ADBE Vector Group","hd":false},{"ty":"gr","it":[{"ind":0,"ty":"sh","ix":1,"ks":{"a":0,"k":{"i":[[0,0],[0,5.762],[-13.207,0],[0,0],[0,-13.217],[3.39,-4.13],[0,0]],"o":[[-3.389,-4.13],[0,-13.217],[0,0],[13.207,0],[0,5.762],[0,0],[0,0]],"v":[[-53.818,14.404],[-59.242,-0.774],[-35.328,-24.706],[35.329,-24.706],[59.242,-0.774],[53.818,14.404],[0.13,24.706]],"c":true},"ix":2},"nm":"Path 1","mn":"ADBE Vector Shape - Group","hd":false},{"ty":"fl","c":{"a":0,"k":[0.023529413635,0.423529441684,0.745098039216,1],"ix":4},"o":{"a":0,"k":100,"ix":5},"r":1,"bm":0,"nm":"Fill 1","mn":"ADBE Vector Graphic - Fill","hd":false},{"ty":"tr","p":{"a":0,"k":[397.007,859.384],"ix":2},"a":{"a":0,"k":[0,0],"ix":1},"s":{"a":0,"k":[100,100],"ix":3},"r":{"a":0,"k":0,"ix":6},"o":{"a":0,"k":100,"ix":7},"sk":{"a":0,"k":0,"ix":4},"sa":{"a":0,"k":0,"ix":5},"nm":"Transform"}],"nm":"Group 2","np":2,"cix":2,"bm":0,"ix":2,"mn":"ADBE Vector Group","hd":false},{"ty":"gr","it":[{"ind":0,"ty":"sh","ix":1,"ks":{"a":0,"k":{"i":[[0,0],[0,2.52],[22.788,0],[8.568,0],[0,0],[0,-13.218],[-0.729,-2.291],[0,0]],"o":[[0.48,-2.378],[0,-20.43],[8.441,0],[0,0],[-13.207,0],[0,2.533],[0,0],[0,0]],"v":[[32.983,15.515],[33.714,8.157],[-4.251,-28.834],[-4.251,-15.682],[-9.8,-15.682],[-33.714,8.25],[-32.592,15.515],[0.13,28.834]],"c":true},"ix":2},"nm":"Path 1","mn":"ADBE Vector Shape - Group","hd":false},{"ty":"fl","c":{"a":0,"k":[0.023529413635,0.423529441684,0.745098039216,1],"ix":4},"o":{"a":0,"k":100,"ix":5},"r":1,"bm":0,"nm":"Fill 1","mn":"ADBE Vector Graphic - Fill","hd":false},{"ty":"tr","p":{"a":0,"k":[397.008,819.163],"ix":2},"a":{"a":0,"k":[0,0],"ix":1},"s":{"a":0,"k":[100,100],"ix":3},"r":{"a":0,"k":0,"ix":6},"o":{"a":0,"k":100,"ix":7},"sk":{"a":0,"k":0,"ix":4},"sa":{"a":0,"k":0,"ix":5},"nm":"Transform"}],"nm":"Group 3","np":2,"cix":2,"bm":0,"ix":3,"mn":"ADBE Vector Group","hd":false},{"ty":"gr","it":[{"ind":0,"ty":"sh","ix":1,"ks":{"a":0,"k":{"i":[[0,0],[-54.609,74.677],[0,0]],"o":[[0,0],[54.612,-74.676],[0,0]],"v":[[-84.031,80.612],[29.42,24.049],[47.115,-98.725]],"c":false},"ix":2},"nm":"Path 1","mn":"ADBE Vector Shape - Group","hd":false},{"ty":"st","c":{"a":0,"k":[1,0.36862745098,0.16862745098,1],"ix":3},"o":{"a":0,"k":100,"ix":4},"w":{"a":0,"k":163.25,"ix":5},"lc":2,"lj":1,"ml":4,"bm":0,"nm":"Stroke 1","mn":"ADBE Vector Graphic - Stroke","hd":false},{"ty":"tr","p":{"a":0,"k":[733.41,596.422],"ix":2},"a":{"a":0,"k":[0,0],"ix":1},"s":{"a":0,"k":[100,100],"ix":3},"r":{"a":0,"k":0,"ix":6},"o":{"a":0,"k":100,"ix":7},"sk":{"a":0,"k":0,"ix":4},"sa":{"a":0,"k":0,"ix":5},"nm":"Transform"}],"nm":"Group 4","np":2,"cix":2,"bm":0,"ix":4,"mn":"ADBE Vector Group","hd":false},{"ty":"gr","it":[{"ind":0,"ty":"sh","ix":1,"ks":{"a":0,"k":{"i":[[0,0],[0,0],[5.14,45.713],[5.989,13.041],[2.661,4.305],[1.124,1.621],[0.496,0.677],[0.23,0.309],[0.109,0.146],[0.054,0.07],[0.014,0.019],[71.813,-55.111],[0.041,0.052],[0.027,0.032],[0.051,0.067],[0.097,0.13],[0.179,0.247],[0.306,0.439],[0.431,0.696],[0.39,0.846],[0.032,0.304],[15.022,-20.542]],"o":[[0,0],[39.587,-54.135],[-2.436,-21.663],[-2.996,-6.519],[-1.333,-2.16],[-0.564,-0.813],[-0.249,-0.339],[-0.114,-0.152],[-0.057,-0.073],[-0.025,-0.035],[-0.04,-0.051],[-71.809,55.11],[-0.013,-0.016],[-0.052,-0.068],[-0.101,-0.133],[-0.195,-0.26],[-0.361,-0.493],[-0.61,-0.881],[-0.856,-1.385],[-0.775,-1.685],[-0.339,-2.997],[0,0]],"v":[[45.125,14.138],[118.195,67.571],[164.407,-85.368],[149.994,-137.74],[141.31,-154],[137.601,-159.672],[136.01,-161.906],[135.292,-162.876],[134.956,-163.323],[134.791,-163.537],[134.712,-163.643],[62.821,-108.635],[-9.067,-53.629],[-9.145,-53.729],[-9.297,-53.932],[-9.595,-54.325],[-10.156,-55.083],[-11.153,-56.482],[-12.706,-58.845],[-14.521,-62.169],[-15.499,-65.134],[-27.942,-39.292]],"c":true},"ix":2},"nm":"Path 1","mn":"ADBE Vector Shape - Group","hd":false},{"ind":1,"ty":"sh","ix":2,"ks":{"a":0,"k":{"i":[[26.633,-86.512],[-0.063,-0.019],[-0.041,-0.014],[-0.084,-0.024],[-0.179,-0.055],[-0.396,-0.111],[-0.935,-0.241],[-2.441,-0.496],[-7.042,-0.586],[-20.991,4.682],[-39.585,54.13],[0,0],[0,0],[3.571,-2.382],[0.357,-0.081],[-1.339,-0.111],[-1.441,-0.292],[-0.981,-0.252],[-0.561,-0.16],[-0.3,-0.087],[-0.154,-0.049],[-0.078,-0.025],[-0.019,-0.005]],"o":[[-26.632,86.512],[0.019,0.005],[0.081,0.024],[0.171,0.052],[0.357,0.105],[0.788,0.222],[1.867,0.479],[4.869,0.994],[14.076,1.176],[44.066,-9.836],[0,0],[0,0],[-7.969,10.898],[-3.514,2.346],[-0.548,0.122],[0.672,0.055],[0.724,0.147],[0.49,0.127],[0.282,0.079],[0.149,0.046],[0.079,0.022],[0.041,0.011],[0.059,0.019]],"v":[[-68.326,70.701],[-94.836,157.251],[-94.714,157.289],[-94.465,157.365],[-93.942,157.522],[-92.815,157.847],[-90.23,158.547],[-83.757,160.031],[-65.803,162.57],[-12.362,158.771],[118.195,67.571],[45.125,14.138],[-27.942,-39.292],[-45.874,-20.82],[-51.794,-17.922],[-50.751,-17.841],[-47.622,-17.364],[-45.072,-16.773],[-43.495,-16.344],[-42.623,-16.093],[-42.165,-15.955],[-41.932,-15.883],[-41.812,-15.849]],"c":true},"ix":2},"nm":"Path 2","mn":"ADBE Vector Shape - Group","hd":false},{"ind":2,"ty":"sh","ix":3,"ks":{"a":0,"k":{"i":[[0,0],[14.708,-47.778],[-47.781,-14.708],[0,0]],"o":[[-47.778,-14.708],[-14.71,47.781],[0,0],[0,0]],"v":[[-41.693,-15.81],[-154.838,44.068],[-94.958,157.214],[-68.326,70.701]],"c":true},"ix":2},"nm":"Path 3","mn":"ADBE Vector Shape - Group","hd":false},{"ty":"mm","mm":1,"nm":"Merge Paths 1","mn":"ADBE Vector Filter - Merge","hd":false},{"ty":"fl","c":{"a":0,"k":[0.901960844152,0.333333333333,0.149019607843,1],"ix":4},"o":{"a":0,"k":100,"ix":5},"r":1,"bm":0,"nm":"Fill 1","mn":"ADBE Vector Graphic - Fill","hd":false},{"ty":"tr","p":{"a":0,"k":[717.703,606.332],"ix":2},"a":{"a":0,"k":[0,0],"ix":1},"s":{"a":0,"k":[100,100],"ix":3},"r":{"a":0,"k":0,"ix":6},"o":{"a":0,"k":100,"ix":7},"sk":{"a":0,"k":0,"ix":4},"sa":{"a":0,"k":0,"ix":5},"nm":"Transform"}],"nm":"Group 5","np":5,"cix":2,"bm":0,"ix":5,"mn":"ADBE Vector Group","hd":false},{"ty":"gr","it":[{"ind":0,"ty":"sh","ix":1,"ks":{"a":0,"k":{"i":[[-10.475,0],[0,0],[0,-10.475],[10.475,0],[0,0],[0,10.475]],"o":[[0,0],[10.475,0],[0,10.475],[0,0],[-10.475,0],[0,-10.475]],"v":[[-307.539,-18.967],[307.539,-18.967],[326.506,0],[307.539,18.967],[-307.539,18.967],[-326.506,0]],"c":true},"ix":2},"nm":"Path 1","mn":"ADBE Vector Shape - Group","hd":false},{"ty":"fl","c":{"a":0,"k":[0.039215686275,0.478431402468,0.792156922583,1],"ix":4},"o":{"a":0,"k":100,"ix":5},"r":1,"bm":0,"nm":"Fill 1","mn":"ADBE Vector Graphic - Fill","hd":false},{"ty":"tr","p":{"a":0,"k":[1040.936,702.679],"ix":2},"a":{"a":0,"k":[0,0],"ix":1},"s":{"a":0,"k":[100,100],"ix":3},"r":{"a":0,"k":0,"ix":6},"o":{"a":0,"k":100,"ix":7},"sk":{"a":0,"k":0,"ix":4},"sa":{"a":0,"k":0,"ix":5},"nm":"Transform"}],"nm":"Group 6","np":2,"cix":2,"bm":0,"ix":6,"mn":"ADBE Vector Group","hd":false},{"ty":"gr","it":[{"ind":0,"ty":"sh","ix":1,"ks":{"a":0,"k":{"i":[[-10.475,0],[0,0],[0,-10.475],[10.476,0],[0,0],[0,10.475]],"o":[[0,0],[10.476,0],[0,10.475],[0,0],[-10.475,0],[0,-10.475]],"v":[[-365.795,-18.967],[365.795,-18.967],[384.762,0],[365.795,18.967],[-365.795,18.967],[-384.762,0]],"c":true},"ix":2},"nm":"Path 1","mn":"ADBE Vector Shape - Group","hd":false},{"ty":"fl","c":{"a":0,"k":[0.039215686275,0.478431402468,0.792156922583,1],"ix":4},"o":{"a":0,"k":100,"ix":5},"r":1,"bm":0,"nm":"Fill 1","mn":"ADBE Vector Graphic - Fill","hd":false},{"ty":"tr","p":{"a":0,"k":[413.665,702.679],"ix":2},"a":{"a":0,"k":[0,0],"ix":1},"s":{"a":0,"k":[100,100],"ix":3},"r":{"a":0,"k":0,"ix":6},"o":{"a":0,"k":100,"ix":7},"sk":{"a":0,"k":0,"ix":4},"sa":{"a":0,"k":0,"ix":5},"nm":"Transform"}],"nm":"Group 7","np":2,"cix":2,"bm":0,"ix":7,"mn":"ADBE Vector Group","hd":false},{"ty":"gr","it":[{"ind":0,"ty":"sh","ix":1,"ks":{"a":0,"k":{"i":[[0,0],[0,0],[0,0],[0,0]],"o":[[0,0],[0,0],[0,0],[0,0]],"v":[[-375.279,-18.967],[375.279,-18.967],[375.279,18.967],[-375.279,18.967]],"c":true},"ix":2},"nm":"Path 1","mn":"ADBE Vector Shape - Group","hd":false},{"ty":"fl","c":{"a":0,"k":[0,0.396078461292,0.717647058824,1],"ix":4},"o":{"a":0,"k":100,"ix":5},"r":1,"bm":0,"nm":"Fill 1","mn":"ADBE Vector Graphic - Fill","hd":false},{"ty":"tr","p":{"a":0,"k":[959.649,716.228],"ix":2},"a":{"a":0,"k":[0,0],"ix":1},"s":{"a":0,"k":[100,100],"ix":3},"r":{"a":0,"k":0,"ix":6},"o":{"a":0,"k":100,"ix":7},"sk":{"a":0,"k":0,"ix":4},"sa":{"a":0,"k":0,"ix":5},"nm":"Transform"}],"nm":"Group 8","np":2,"cix":2,"bm":0,"ix":8,"mn":"ADBE Vector Group","hd":false},{"ty":"gr","it":[{"ind":0,"ty":"sh","ix":1,"ks":{"a":0,"k":{"i":[[0,0],[0,0],[0,0],[0,0]],"o":[[0,0],[0,0],[0,0],[0,0]],"v":[[-375.279,-18.967],[375.279,-18.967],[375.279,18.967],[-375.279,18.967]],"c":true},"ix":2},"nm":"Path 1","mn":"ADBE Vector Shape - Group","hd":false},{"ty":"fl","c":{"a":0,"k":[0.023529413635,0.423529441684,0.745098039216,1],"ix":4},"o":{"a":0,"k":100,"ix":5},"r":1,"bm":0,"nm":"Fill 1","mn":"ADBE Vector Graphic - Fill","hd":false},{"ty":"tr","p":{"a":0,"k":[423.149,716.228],"ix":2},"a":{"a":0,"k":[0,0],"ix":1},"s":{"a":0,"k":[100,100],"ix":3},"r":{"a":0,"k":0,"ix":6},"o":{"a":0,"k":100,"ix":7},"sk":{"a":0,"k":0,"ix":4},"sa":{"a":0,"k":0,"ix":5},"nm":"Transform"}],"nm":"Group 9","np":2,"cix":2,"bm":0,"ix":9,"mn":"ADBE Vector Group","hd":false},{"ty":"gr","it":[{"ind":0,"ty":"sh","ix":1,"ks":{"a":0,"k":{"i":[[0,0],[-14.965,0],[0,0],[0,-14.965],[0,0],[0,0],[0,14.965]],"o":[[0,-14.965],[0,0],[14.965,0],[0,0],[0,0],[-14.965,0],[0,0]],"v":[[-366.519,-110.688],[-339.423,-137.784],[339.424,-137.784],[366.519,-110.688],[366.519,137.784],[-339.423,137.784],[-366.519,110.689]],"c":true},"ix":2},"nm":"Path 1","mn":"ADBE Vector Shape - Group","hd":false},{"ty":"fl","c":{"a":0,"k":[0.039215686275,0.478431402468,0.792156922583,1],"ix":4},"o":{"a":0,"k":100,"ix":5},"r":1,"bm":0,"nm":"Fill 1","mn":"ADBE Vector Graphic - Fill","hd":false},{"ty":"tr","p":{"a":0,"k":[413.775,821.18],"ix":2},"a":{"a":0,"k":[0,0],"ix":1},"s":{"a":0,"k":[100,100],"ix":3},"r":{"a":0,"k":0,"ix":6},"o":{"a":0,"k":100,"ix":7},"sk":{"a":0,"k":0,"ix":4},"sa":{"a":0,"k":0,"ix":5},"nm":"Transform"}],"nm":"Group 10","np":2,"cix":2,"bm":0,"ix":10,"mn":"ADBE Vector Group","hd":false},{"ty":"gr","it":[{"ind":0,"ty":"sh","ix":1,"ks":{"a":0,"k":{"i":[[-14.965,0],[0,0],[0,-14.965],[0,0],[14.965,0],[0,0],[0,14.965],[0,0]],"o":[[0,0],[14.965,0],[0,0],[0,14.965],[0,0],[-14.965,0],[0,0],[0,-14.965]],"v":[[-617.268,-137.784],[617.268,-137.784],[644.365,-110.688],[644.365,110.688],[617.268,137.784],[-617.268,137.784],[-644.365,110.688],[-644.365,-110.688]],"c":true},"ix":2},"nm":"Path 1","mn":"ADBE Vector Shape - Group","hd":false},{"ty":"fl","c":{"a":0,"k":[0.023529413635,0.423529441684,0.745098039216,1],"ix":4},"o":{"a":0,"k":100,"ix":5},"r":1,"bm":0,"nm":"Fill 1","mn":"ADBE Vector Graphic - Fill","hd":false},{"ty":"tr","p":{"a":0,"k":[691.62,821.179],"ix":2},"a":{"a":0,"k":[0,0],"ix":1},"s":{"a":0,"k":[100,100],"ix":3},"r":{"a":0,"k":0,"ix":6},"o":{"a":0,"k":100,"ix":7},"sk":{"a":0,"k":0,"ix":4},"sa":{"a":0,"k":0,"ix":5},"nm":"Transform"}],"nm":"Group 11","np":2,"cix":2,"bm":0,"ix":11,"mn":"ADBE Vector Group","hd":false},{"ty":"gr","it":[{"ind":0,"ty":"sh","ix":1,"ks":{"a":0,"k":{"i":[[-24.623,0],[0,0],[0,-24.623],[24.624,0],[0,0],[0,24.624]],"o":[[0,0],[24.624,0],[0,24.624],[0,0],[-24.623,0],[0,-24.623]],"v":[[-46.236,-44.585],[46.237,-44.585],[90.821,-0.001],[46.237,44.584],[-46.236,44.584],[-90.821,-0.001]],"c":true},"ix":2},"nm":"Path 1","mn":"ADBE Vector Shape - Group","hd":false},{"ty":"fl","c":{"a":0,"k":[1,0.36862745098,0.16862745098,1],"ix":4},"o":{"a":0,"k":100,"ix":5},"r":1,"bm":0,"nm":"Fill 1","mn":"ADBE Vector Graphic - Fill","hd":false},{"ty":"tr","p":{"a":0,"k":[422.437,895.763],"ix":2},"a":{"a":0,"k":[0,0],"ix":1},"s":{"a":0,"k":[100,100],"ix":3},"r":{"a":0,"k":0,"ix":6},"o":{"a":0,"k":100,"ix":7},"sk":{"a":0,"k":0,"ix":4},"sa":{"a":0,"k":0,"ix":5},"nm":"Transform"}],"nm":"Group 12","np":2,"cix":2,"bm":0,"ix":12,"mn":"ADBE Vector Group","hd":false},{"ty":"gr","it":[{"ind":0,"ty":"sh","ix":1,"ks":{"a":0,"k":{"i":[[-24.623,0],[0,0],[0,-24.623],[24.624,0],[0,0],[0,24.624]],"o":[[0,0],[24.624,0],[0,24.624],[0,0],[-24.623,0],[0,-24.623]],"v":[[-46.237,-44.585],[46.236,-44.585],[90.821,-0.001],[46.236,44.584],[-46.237,44.584],[-90.821,-0.001]],"c":true},"ix":2},"nm":"Path 1","mn":"ADBE Vector Shape - Group","hd":false},{"ty":"fl","c":{"a":0,"k":[1,0.36862745098,0.16862745098,1],"ix":4},"o":{"a":0,"k":100,"ix":5},"r":1,"bm":0,"nm":"Fill 1","mn":"ADBE Vector Graphic - Fill","hd":false},{"ty":"tr","p":{"a":0,"k":[654.446,895.763],"ix":2},"a":{"a":0,"k":[0,0],"ix":1},"s":{"a":0,"k":[100,100],"ix":3},"r":{"a":0,"k":0,"ix":6},"o":{"a":0,"k":100,"ix":7},"sk":{"a":0,"k":0,"ix":4},"sa":{"a":0,"k":0,"ix":5},"nm":"Transform"}],"nm":"Group 13","np":2,"cix":2,"bm":0,"ix":13,"mn":"ADBE Vector Group","hd":false},{"ty":"gr","it":[{"ind":0,"ty":"sh","ix":1,"ks":{"a":0,"k":{"i":[[82.009,39.536],[0,0],[0,0]],"o":[[-82.011,-39.533],[0,0],[0,0]],"v":[[21.627,-50.989],[-126.008,-57.386],[126.008,90.522]],"c":true},"ix":2},"nm":"Path 1","mn":"ADBE Vector Shape - Group","hd":false},{"ty":"fl","c":{"a":0,"k":[1,0.36862745098,0.16862745098,1],"ix":4},"o":{"a":0,"k":100,"ix":5},"r":1,"bm":0,"nm":"Fill 1","mn":"ADBE Vector Graphic - Fill","hd":false},{"ty":"tr","p":{"a":0,"k":[695.229,175.406],"ix":2},"a":{"a":0,"k":[0,0],"ix":1},"s":{"a":0,"k":[100,100],"ix":3},"r":{"a":0,"k":0,"ix":6},"o":{"a":0,"k":100,"ix":7},"sk":{"a":0,"k":0,"ix":4},"sa":{"a":0,"k":0,"ix":5},"nm":"Transform"}],"nm":"Group 14","np":2,"cix":2,"bm":0,"ix":14,"mn":"ADBE Vector Group","hd":false},{"ty":"gr","it":[{"ind":0,"ty":"sh","ix":1,"ks":{"a":0,"k":{"i":[[0,0],[-0.149,-28.806],[0,0],[47.136,32.643],[0,0]],"o":[[24.88,-14.521],[0,0],[0,0],[-47.139,-32.642],[0,0]],"v":[[36.98,-84.81],[93.28,-52.678],[94.079,99.331],[17.831,49.835],[-94.078,-8.318]],"c":true},"ix":2},"nm":"Path 1","mn":"ADBE Vector Shape - Group","hd":false},{"ty":"fl","c":{"a":0,"k":[0.996078491211,0.611764705882,0.36862745098,1],"ix":4},"o":{"a":0,"k":100,"ix":5},"r":1,"bm":0,"nm":"Fill 1","mn":"ADBE Vector Graphic - Fill","hd":false},{"ty":"tr","p":{"a":0,"k":[708.053,123.382],"ix":2},"a":{"a":0,"k":[0,0],"ix":1},"s":{"a":0,"k":[100,100],"ix":3},"r":{"a":0,"k":0,"ix":6},"o":{"a":0,"k":100,"ix":7},"sk":{"a":0,"k":0,"ix":4},"sa":{"a":0,"k":0,"ix":5},"nm":"Transform"}],"nm":"Group 15","np":2,"cix":2,"bm":0,"ix":15,"mn":"ADBE Vector Group","hd":false},{"ty":"gr","it":[{"ind":0,"ty":"sh","ix":1,"ks":{"a":0,"k":{"i":[[0,0],[-0.068,-44.966],[0,0],[0,0]],"o":[[38.918,-22.522],[0,0],[0,0],[0,0]],"v":[[33.991,-104.072],[121.687,-53.589],[121.966,126.594],[-121.965,-13.826]],"c":true},"ix":2},"nm":"Path 1","mn":"ADBE Vector Shape - Group","hd":false},{"ty":"fl","c":{"a":0,"k":[1,0.36862745098,0.16862745098,1],"ix":4},"o":{"a":0,"k":100,"ix":5},"r":1,"bm":0,"nm":"Fill 1","mn":"ADBE Vector Graphic - Fill","hd":false},{"ty":"tr","p":{"a":0,"k":[698.524,127.494],"ix":2},"a":{"a":0,"k":[0,0],"ix":1},"s":{"a":0,"k":[100,100],"ix":3},"r":{"a":0,"k":0,"ix":6},"o":{"a":0,"k":100,"ix":7},"sk":{"a":0,"k":0,"ix":4},"sa":{"a":0,"k":0,"ix":5},"nm":"Transform"}],"nm":"Group 16","np":2,"cix":2,"bm":0,"ix":16,"mn":"ADBE Vector Group","hd":false},{"ty":"gr","it":[{"ind":0,"ty":"sh","ix":1,"ks":{"a":0,"k":{"i":[[0,0],[-2.729,2.978],[0,0],[6.162,0],[0,0],[-4.309,-4.702]],"o":[[2.731,2.978],[0,0],[4.308,-4.702],[0,0],[-6.159,0],[0,0]],"v":[[-4.976,12.85],[4.974,12.85],[19.695,-3.212],[14.72,-15.828],[-14.722,-15.828],[-19.694,-3.212]],"c":true},"ix":2},"nm":"Path 1","mn":"ADBE Vector Shape - Group","hd":false},{"ty":"fl","c":{"a":0,"k":[0.839215746113,0.235294132607,0,1],"ix":4},"o":{"a":0,"k":100,"ix":5},"r":1,"bm":0,"nm":"Fill 1","mn":"ADBE Vector Graphic - Fill","hd":false},{"ty":"tr","p":{"a":0,"k":[451.028,333.629],"ix":2},"a":{"a":0,"k":[0,0],"ix":1},"s":{"a":0,"k":[100,100],"ix":3},"r":{"a":0,"k":0,"ix":6},"o":{"a":0,"k":100,"ix":7},"sk":{"a":0,"k":0,"ix":4},"sa":{"a":0,"k":0,"ix":5},"nm":"Transform"}],"nm":"Group 17","np":2,"cix":2,"bm":0,"ix":17,"mn":"ADBE Vector Group","hd":false},{"ty":"gr","it":[{"ind":0,"ty":"sh","ix":1,"ks":{"a":0,"k":{"i":[[0,26.283],[26.283,0],[0,0],[0,-26.283],[-26.283,0],[0,0]],"o":[[0,-26.283],[0,0],[-26.283,0],[0,26.283],[0,0],[26.283,0]],"v":[[74.006,-0.001],[26.417,-47.59],[-26.414,-47.59],[-74.006,-0.001],[-26.414,47.59],[26.417,47.59]],"c":true},"ix":2},"nm":"Path 1","mn":"ADBE Vector Shape - Group","hd":false},{"ty":"fl","c":{"a":0,"k":[0.996078491211,0.611764705882,0.36862745098,1],"ix":4},"o":{"a":0,"k":100,"ix":5},"r":1,"bm":0,"nm":"Fill 1","mn":"ADBE Vector Graphic - Fill","hd":false},{"ty":"tr","p":{"a":0,"k":[437.23,376.399],"ix":2},"a":{"a":0,"k":[0,0],"ix":1},"s":{"a":0,"k":[100,100],"ix":3},"r":{"a":0,"k":0,"ix":6},"o":{"a":0,"k":100,"ix":7},"sk":{"a":0,"k":0,"ix":4},"sa":{"a":0,"k":0,"ix":5},"nm":"Transform"}],"nm":"Group 18","np":2,"cix":2,"bm":0,"ix":18,"mn":"ADBE Vector Group","hd":false},{"ty":"gr","it":[{"ind":0,"ty":"sh","ix":1,"ks":{"a":0,"k":{"i":[[0,26.283],[-26.285,0],[0,0],[0,-26.283],[26.283,0],[0,0]],"o":[[0,-26.283],[0,0],[26.283,0],[0,26.283],[0,0],[-26.283,0]],"v":[[-74.006,-0.001],[-26.415,-47.59],[26.417,-47.59],[74.006,-0.001],[26.417,47.59],[-26.415,47.59]],"c":true},"ix":2},"nm":"Path 1","mn":"ADBE Vector Shape - Group","hd":false},{"ty":"fl","c":{"a":0,"k":[0.996078491211,0.611764705882,0.36862745098,1],"ix":4},"o":{"a":0,"k":100,"ix":5},"r":1,"bm":0,"nm":"Fill 1","mn":"ADBE Vector Graphic - Fill","hd":false},{"ty":"tr","p":{"a":0,"k":[464.825,376.399],"ix":2},"a":{"a":0,"k":[0,0],"ix":1},"s":{"a":0,"k":[100,100],"ix":3},"r":{"a":0,"k":0,"ix":6},"o":{"a":0,"k":100,"ix":7},"sk":{"a":0,"k":0,"ix":4},"sa":{"a":0,"k":0,"ix":5},"nm":"Transform"}],"nm":"Group 19","np":2,"cix":2,"bm":0,"ix":19,"mn":"ADBE Vector Group","hd":false},{"ty":"gr","it":[{"ind":0,"ty":"sh","ix":1,"ks":{"a":0,"k":{"i":[[4.427,-1.186],[0,0],[1.186,4.426],[-4.426,1.186],[0,0],[-1.186,-4.426]],"o":[[0,0],[-4.427,1.186],[-1.186,-4.427],[0,0],[4.426,-1.186],[1.187,4.427]],"v":[[25.048,1.879],[-20.753,14.151],[-30.916,8.284],[-25.049,-1.879],[20.753,-14.151],[30.915,-8.284]],"c":true},"ix":2},"nm":"Path 1","mn":"ADBE Vector Shape - Group","hd":false},{"ty":"fl","c":{"a":0,"k":[0.901960844152,0.333333333333,0.149019607843,1],"ix":4},"o":{"a":0,"k":100,"ix":5},"r":1,"bm":0,"nm":"Fill 1","mn":"ADBE Vector Graphic - Fill","hd":false},{"ty":"tr","p":{"a":0,"k":[271.086,387.608],"ix":2},"a":{"a":0,"k":[0,0],"ix":1},"s":{"a":0,"k":[100,100],"ix":3},"r":{"a":0,"k":0,"ix":6},"o":{"a":0,"k":100,"ix":7},"sk":{"a":0,"k":0,"ix":4},"sa":{"a":0,"k":0,"ix":5},"nm":"Transform"}],"nm":"Group 20","np":2,"cix":2,"bm":0,"ix":20,"mn":"ADBE Vector Group","hd":false},{"ty":"gr","it":[{"ind":0,"ty":"sh","ix":1,"ks":{"a":0,"k":{"i":[[4.427,1.186],[0,0],[1.186,-4.426],[-4.426,-1.186],[0,0],[-1.186,4.426]],"o":[[0,0],[-4.427,-1.186],[-1.186,4.427],[0,0],[4.426,1.186],[1.187,-4.427]],"v":[[25.048,-1.879],[-20.753,-14.151],[-30.916,-8.284],[-25.049,1.879],[20.753,14.151],[30.915,8.284]],"c":true},"ix":2},"nm":"Path 1","mn":"ADBE Vector Shape - Group","hd":false},{"ty":"fl","c":{"a":0,"k":[0.901960844152,0.333333333333,0.149019607843,1],"ix":4},"o":{"a":0,"k":100,"ix":5},"r":1,"bm":0,"nm":"Fill 1","mn":"ADBE Vector Graphic - Fill","hd":false},{"ty":"tr","p":{"a":0,"k":[271.086,325.715],"ix":2},"a":{"a":0,"k":[0,0],"ix":1},"s":{"a":0,"k":[100,100],"ix":3},"r":{"a":0,"k":0,"ix":6},"o":{"a":0,"k":100,"ix":7},"sk":{"a":0,"k":0,"ix":4},"sa":{"a":0,"k":0,"ix":5},"nm":"Transform"}],"nm":"Group 21","np":2,"cix":2,"bm":0,"ix":21,"mn":"ADBE Vector Group","hd":false},{"ty":"gr","it":[{"ind":0,"ty":"sh","ix":1,"ks":{"a":0,"k":{"i":[[4.583,0],[0,0],[0,-4.583],[-4.583,0],[0,0],[0,4.583]],"o":[[0,0],[-4.583,0],[0,4.583],[0,0],[4.583,0],[0,-4.583]],"v":[[23.709,-8.298],[-23.708,-8.298],[-32.006,0],[-23.708,8.298],[23.709,8.298],[32.007,0]],"c":true},"ix":2},"nm":"Path 1","mn":"ADBE Vector Shape - Group","hd":false},{"ty":"fl","c":{"a":0,"k":[0.901960844152,0.333333333333,0.149019607843,1],"ix":4},"o":{"a":0,"k":100,"ix":5},"r":1,"bm":0,"nm":"Fill 1","mn":"ADBE Vector Graphic - Fill","hd":false},{"ty":"tr","p":{"a":0,"k":[255.725,356.538],"ix":2},"a":{"a":0,"k":[0,0],"ix":1},"s":{"a":0,"k":[100,100],"ix":3},"r":{"a":0,"k":0,"ix":6},"o":{"a":0,"k":100,"ix":7},"sk":{"a":0,"k":0,"ix":4},"sa":{"a":0,"k":0,"ix":5},"nm":"Transform"}],"nm":"Group 22","np":2,"cix":2,"bm":0,"ix":22,"mn":"ADBE Vector Group","hd":false},{"ty":"gr","it":[{"ind":0,"ty":"sh","ix":1,"ks":{"a":0,"k":{"i":[[-4.427,-1.186],[0,0],[-1.186,4.426],[4.426,1.186],[0,0],[1.186,-4.426]],"o":[[0,0],[4.427,1.186],[1.186,-4.427],[0,0],[-4.426,-1.186],[-1.187,4.427]],"v":[[-25.048,1.879],[20.753,14.151],[30.916,8.284],[25.049,-1.879],[-20.753,-14.151],[-30.915,-8.284]],"c":true},"ix":2},"nm":"Path 1","mn":"ADBE Vector Shape - Group","hd":false},{"ty":"fl","c":{"a":0,"k":[0.901960844152,0.333333333333,0.149019607843,1],"ix":4},"o":{"a":0,"k":100,"ix":5},"r":1,"bm":0,"nm":"Fill 1","mn":"ADBE Vector Graphic - Fill","hd":false},{"ty":"tr","p":{"a":0,"k":[646.984,387.608],"ix":2},"a":{"a":0,"k":[0,0],"ix":1},"s":{"a":0,"k":[100,100],"ix":3},"r":{"a":0,"k":0,"ix":6},"o":{"a":0,"k":100,"ix":7},"sk":{"a":0,"k":0,"ix":4},"sa":{"a":0,"k":0,"ix":5},"nm":"Transform"}],"nm":"Group 23","np":2,"cix":2,"bm":0,"ix":23,"mn":"ADBE Vector Group","hd":false},{"ty":"gr","it":[{"ind":0,"ty":"sh","ix":1,"ks":{"a":0,"k":{"i":[[-4.427,1.186],[0,0],[-1.186,-4.426],[4.426,-1.186],[0,0],[1.186,4.426]],"o":[[0,0],[4.427,-1.186],[1.186,4.427],[0,0],[-4.426,1.186],[-1.187,-4.427]],"v":[[-25.048,-1.879],[20.753,-14.151],[30.916,-8.284],[25.049,1.879],[-20.753,14.151],[-30.915,8.284]],"c":true},"ix":2},"nm":"Path 1","mn":"ADBE Vector Shape - Group","hd":false},{"ty":"fl","c":{"a":0,"k":[0.901960844152,0.333333333333,0.149019607843,1],"ix":4},"o":{"a":0,"k":100,"ix":5},"r":1,"bm":0,"nm":"Fill 1","mn":"ADBE Vector Graphic - Fill","hd":false},{"ty":"tr","p":{"a":0,"k":[646.984,325.715],"ix":2},"a":{"a":0,"k":[0,0],"ix":1},"s":{"a":0,"k":[100,100],"ix":3},"r":{"a":0,"k":0,"ix":6},"o":{"a":0,"k":100,"ix":7},"sk":{"a":0,"k":0,"ix":4},"sa":{"a":0,"k":0,"ix":5},"nm":"Transform"}],"nm":"Group 24","np":2,"cix":2,"bm":0,"ix":24,"mn":"ADBE Vector Group","hd":false},{"ty":"gr","it":[{"ind":0,"ty":"sh","ix":1,"ks":{"a":0,"k":{"i":[[-4.583,0],[0,0],[0,-4.583],[4.583,0],[0,0],[0,4.583]],"o":[[0,0],[4.583,0],[0,4.583],[0,0],[-4.583,0],[0,-4.583]],"v":[[-23.708,-8.298],[23.708,-8.298],[32.006,0],[23.708,8.298],[-23.708,8.298],[-32.007,0]],"c":true},"ix":2},"nm":"Path 1","mn":"ADBE Vector Shape - Group","hd":false},{"ty":"fl","c":{"a":0,"k":[0.901960844152,0.333333333333,0.149019607843,1],"ix":4},"o":{"a":0,"k":100,"ix":5},"r":1,"bm":0,"nm":"Fill 1","mn":"ADBE Vector Graphic - Fill","hd":false},{"ty":"tr","p":{"a":0,"k":[662.355,356.538],"ix":2},"a":{"a":0,"k":[0,0],"ix":1},"s":{"a":0,"k":[100,100],"ix":3},"r":{"a":0,"k":0,"ix":6},"o":{"a":0,"k":100,"ix":7},"sk":{"a":0,"k":0,"ix":4},"sa":{"a":0,"k":0,"ix":5},"nm":"Transform"}],"nm":"Group 25","np":2,"cix":2,"bm":0,"ix":25,"mn":"ADBE Vector Group","hd":false},{"ty":"gr","it":[{"ind":0,"ty":"sh","ix":1,"ks":{"a":0,"k":{"i":[[-75.239,0],[0,0],[0,-75.239],[0,0],[75.239,0],[0,75.238],[0,0]],"o":[[0,0],[75.239,0],[0,0],[0,75.238],[-75.239,0],[0,0],[0,-75.239]],"v":[[0,-163.475],[0,-163.475],[136.232,-27.243],[136.232,27.244],[0,163.475],[-136.232,27.244],[-136.232,-27.243]],"c":true},"ix":2},"nm":"Path 1","mn":"ADBE Vector Shape - Group","hd":false},{"ty":"fl","c":{"a":0,"k":[0.996078491211,0.611764705882,0.36862745098,1],"ix":4},"o":{"a":0,"k":100,"ix":5},"r":1,"bm":0,"nm":"Fill 1","mn":"ADBE Vector Graphic - Fill","hd":false},{"ty":"tr","p":{"a":0,"k":[452.425,634.866],"ix":2},"a":{"a":0,"k":[0,0],"ix":1},"s":{"a":0,"k":[100,100],"ix":3},"r":{"a":0,"k":0,"ix":6},"o":{"a":0,"k":100,"ix":7},"sk":{"a":0,"k":0,"ix":4},"sa":{"a":0,"k":0,"ix":5},"nm":"Transform"}],"nm":"Group 26","np":2,"cix":2,"bm":0,"ix":26,"mn":"ADBE Vector Group","hd":false},{"ty":"gr","it":[{"ind":0,"ty":"sh","ix":1,"ks":{"a":0,"k":{"i":[[0,0],[-16.477,-118.903],[0,0],[96.822,0],[0,0],[-11.09,94.814],[0,0],[-121.986,0]],"o":[[120.038,0],[0,0],[13.29,95.903],[0,0],[-95.457,0],[0,0],[14.171,-121.159],[0,0]],"v":[[62.706,-385.734],[300.871,-178.299],[353.89,204.292],[195.858,385.734],[-197.628,385.734],[-356.091,207.658],[-311.539,-173.227],[-72.728,-385.734]],"c":true},"ix":2},"nm":"Path 1","mn":"ADBE Vector Shape - Group","hd":false},{"ty":"st","c":{"a":0,"k":[0.901960844152,0.333333333333,0.149019607843,1],"ix":3},"o":{"a":0,"k":100,"ix":4},"w":{"a":0,"k":7.325,"ix":5},"lc":1,"lj":1,"ml":4,"bm":0,"nm":"Stroke 1","mn":"ADBE Vector Graphic - Stroke","hd":false},{"ty":"fl","c":{"a":0,"k":[1,0.36862745098,0.16862745098,1],"ix":4},"o":{"a":0,"k":100,"ix":5},"r":1,"bm":0,"nm":"Fill 1","mn":"ADBE Vector Graphic - Fill","hd":false},{"ty":"tr","p":{"a":0,"k":[554.111,439.879],"ix":2},"a":{"a":0,"k":[0,0],"ix":1},"s":{"a":0,"k":[100,100],"ix":3},"r":{"a":0,"k":0,"ix":6},"o":{"a":0,"k":100,"ix":7},"sk":{"a":0,"k":0,"ix":4},"sa":{"a":0,"k":0,"ix":5},"nm":"Transform"}],"nm":"Group 27","np":3,"cix":2,"bm":0,"ix":27,"mn":"ADBE Vector Group","hd":false},{"ty":"gr","it":[{"ind":0,"ty":"sh","ix":1,"ks":{"a":0,"k":{"i":[[0,0],[4.837,-41.275],[0,0],[-19.484,12.283],[0,0]],"o":[[-10.183,-40.291],[0,0],[0,0],[19.485,-12.282],[0,0]],"v":[[32.41,-64.541],[-41.059,-59.728],[-60.353,104.832],[4.405,70.862],[60.353,46.026]],"c":true},"ix":2},"nm":"Path 1","mn":"ADBE Vector Shape - Group","hd":false},{"ty":"fl","c":{"a":0,"k":[0.996078491211,0.611764705882,0.36862745098,1],"ix":4},"o":{"a":0,"k":100,"ix":5},"r":1,"bm":0,"nm":"Fill 1","mn":"ADBE Vector Graphic - Fill","hd":false},{"ty":"tr","p":{"a":0,"k":[387.989,143.301],"ix":2},"a":{"a":0,"k":[0,0],"ix":1},"s":{"a":0,"k":[100,100],"ix":3},"r":{"a":0,"k":0,"ix":6},"o":{"a":0,"k":100,"ix":7},"sk":{"a":0,"k":0,"ix":4},"sa":{"a":0,"k":0,"ix":5},"nm":"Transform"}],"nm":"Group 28","np":2,"cix":2,"bm":0,"ix":28,"mn":"ADBE Vector Group","hd":false},{"ty":"gr","it":[{"ind":0,"ty":"sh","ix":1,"ks":{"a":0,"k":{"i":[[0,0],[6.641,-44.473],[0,0],[0,0]],"o":[[-35.208,-27.969],[0,0],[0,0],[0,0]],"v":[[-21.95,-112.022],[-116.085,-74.9],[-148.179,139.99],[148.179,23.123]],"c":true},"ix":2},"nm":"Path 1","mn":"ADBE Vector Shape - Group","hd":false},{"ty":"fl","c":{"a":0,"k":[1,0.36862745098,0.16862745098,1],"ix":4},"o":{"a":0,"k":100,"ix":5},"r":1,"bm":0,"nm":"Fill 1","mn":"ADBE Vector Graphic - Fill","hd":false},{"ty":"tr","p":{"a":0,"k":[450.047,140.241],"ix":2},"a":{"a":0,"k":[0,0],"ix":1},"s":{"a":0,"k":[100,100],"ix":3},"r":{"a":0,"k":0,"ix":6},"o":{"a":0,"k":100,"ix":7},"sk":{"a":0,"k":0,"ix":4},"sa":{"a":0,"k":0,"ix":5},"nm":"Transform"}],"nm":"Group 29","np":2,"cix":2,"bm":0,"ix":29,"mn":"ADBE Vector Group","hd":false},{"ty":"gr","it":[{"ind":0,"ty":"sh","ix":1,"ks":{"a":0,"k":{"i":[[0,0],[-36.875,28.762],[-22.238,47.556],[0,0]],"o":[[0,0],[47.502,-37.054],[27.843,-59.547],[0,0]],"v":[[-102.271,57.109],[3.547,94.163],[18.049,-63.378],[102.271,-107.808]],"c":false},"ix":2},"nm":"Path 1","mn":"ADBE Vector Shape - Group","hd":false},{"ty":"st","c":{"a":0,"k":[1,0.36862745098,0.16862745098,1],"ix":3},"o":{"a":0,"k":100,"ix":4},"w":{"a":0,"k":108.543,"ix":5},"lc":2,"lj":1,"ml":4,"bm":0,"nm":"Stroke 1","mn":"ADBE Vector Graphic - Stroke","hd":false},{"ty":"tr","p":{"a":0,"k":[895.691,583.982],"ix":2},"a":{"a":0,"k":[0,0],"ix":1},"s":{"a":0,"k":[100,100],"ix":3},"r":{"a":0,"k":0,"ix":6},"o":{"a":0,"k":100,"ix":7},"sk":{"a":0,"k":0,"ix":4},"sa":{"a":0,"k":0,"ix":5},"nm":"Transform"}],"nm":"Group 30","np":2,"cix":2,"bm":0,"ix":30,"mn":"ADBE Vector Group","hd":false},{"ty":"gr","it":[{"ind":0,"ty":"sh","ix":1,"ks":{"a":0,"k":{"i":[[0,0],[-56.649,73.14],[0,0]],"o":[[0,0],[56.647,-73.143],[0,0]],"v":[[-51.177,98.907],[-28.218,-25.764],[84.867,-76.745]],"c":false},"ix":2},"nm":"Path 1","mn":"ADBE Vector Shape - Group","hd":false},{"ty":"st","c":{"a":0,"k":[1,0.36862745098,0.16862745098,1],"ix":3},"o":{"a":0,"k":100,"ix":4},"w":{"a":0,"k":163.25,"ix":5},"lc":2,"lj":1,"ml":4,"bm":0,"nm":"Stroke 1","mn":"ADBE Vector Graphic - Stroke","hd":false},{"ty":"tr","p":{"a":0,"k":[248.117,622.052],"ix":2},"a":{"a":0,"k":[0,0],"ix":1},"s":{"a":0,"k":[100,100],"ix":3},"r":{"a":0,"k":0,"ix":6},"o":{"a":0,"k":100,"ix":7},"sk":{"a":0,"k":0,"ix":4},"sa":{"a":0,"k":0,"ix":5},"nm":"Transform"}],"nm":"Group 31","np":2,"cix":2,"bm":0,"ix":31,"mn":"ADBE Vector Group","hd":false},{"ty":"gr","it":[{"ind":0,"ty":"sh","ix":1,"ks":{"a":0,"k":{"i":[[0,0],[0,0],[-45.351,7.712],[-14.188,-2.146],[-4.877,-1.366],[-1.87,-0.631],[-0.792,-0.288],[-0.361,-0.138],[-0.17,-0.065],[-0.082,-0.03],[-0.021,-0.008],[33.087,-84.255],[-0.06,-0.025],[-0.041,-0.017],[-0.079,-0.03],[-0.152,-0.057],[-0.287,-0.106],[-0.51,-0.17],[-0.789,-0.222],[-0.918,-0.141],[-0.301,0.052],[15.583,-20.119]],"o":[[0,0],[41.067,-53.024],[21.492,-3.652],[7.096,1.073],[2.441,0.683],[0.935,0.317],[0.393,0.146],[0.178,0.068],[0.084,0.035],[0.043,0.016],[0.06,0.025],[-33.086,84.255],[0.019,0.008],[0.079,0.03],[0.157,0.059],[0.304,0.114],[0.572,0.208],[1.013,0.345],[1.568,0.439],[1.838,0.277],[2.972,-0.504],[0,0]],"v":[[-10.176,-40.991],[-81.742,-96.418],[52.438,-183.15],[106.752,-183.792],[124.784,-179.947],[131.26,-177.953],[133.848,-177.042],[134.978,-176.62],[135.5,-176.422],[135.75,-176.324],[135.874,-176.276],[102.909,-91.972],[69.942,-7.668],[70.061,-7.622],[70.297,-7.53],[70.76,-7.354],[71.643,-7.023],[73.264,-6.455],[75.963,-5.615],[79.658,-4.791],[82.78,-4.672],[61.39,14.437]],"c":true},"ix":2},"nm":"Path 1","mn":"ADBE Vector Shape - Group","hd":false},{"ind":1,"ty":"sh","ix":2,"ks":{"a":0,"k":{"i":[[75.765,-49.534],[0.035,0.051],[0.023,0.035],[0.048,0.073],[0.101,0.157],[0.217,0.35],[0.49,0.832],[1.153,2.209],[2.514,6.606],[1.307,21.465],[-41.063,53.018],[0,0],[0,0],[1.301,-4.092],[-0.022,-0.363],[0.477,1.255],[0.68,1.304],[0.514,0.873],[0.309,0.496],[0.169,0.263],[0.087,0.135],[0.045,0.07],[0.011,0.016]],"o":[[-75.765,49.534],[-0.012,-0.019],[-0.047,-0.073],[-0.096,-0.149],[-0.2,-0.314],[-0.432,-0.693],[-0.979,-1.664],[-2.302,-4.405],[-5.024,-13.201],[-2.745,-45.066],[0,0],[0,0],[-8.267,10.673],[-1.282,4.026],[0.032,0.561],[-0.241,-0.628],[-0.344,-0.655],[-0.257,-0.436],[-0.154,-0.246],[-0.084,-0.132],[-0.044,-0.068],[-0.022,-0.033],[-0.034,-0.052]],"v":[[-33.135,83.68],[-108.969,133.109],[-109.039,133],[-109.181,132.781],[-109.476,132.323],[-110.101,131.328],[-111.487,129.039],[-114.707,123.229],[-122.116,106.679],[-133.251,54.276],[-81.742,-96.418],[-10.176,-40.991],[61.39,14.437],[48.601,36.78],[47.455,43.269],[47.089,42.291],[45.764,39.416],[44.488,37.129],[43.641,35.731],[43.157,34.964],[42.9,34.561],[42.766,34.355],[42.699,34.252]],"c":true},"ix":2},"nm":"Path 2","mn":"ADBE Vector Shape - Group","hd":false},{"ind":2,"ty":"sh","ix":3,"ks":{"a":0,"k":{"i":[[0,0],[41.843,-27.359],[27.357,41.842],[0,0]],"o":[[27.358,41.844],[-41.844,27.356],[0,0],[0,0]],"v":[[42.63,34.146],[16.399,159.446],[-108.9,133.214],[-33.135,83.68]],"c":true},"ix":2},"nm":"Path 3","mn":"ADBE Vector Shape - Group","hd":false},{"ty":"mm","mm":1,"nm":"Merge Paths 1","mn":"ADBE Vector Filter - Merge","hd":false},{"ty":"fl","c":{"a":0,"k":[0.901960844152,0.333333333333,0.149019607843,1],"ix":4},"o":{"a":0,"k":100,"ix":5},"r":1,"bm":0,"nm":"Fill 1","mn":"ADBE Vector Graphic - Fill","hd":false},{"ty":"tr","p":{"a":0,"k":[230.075,637.278],"ix":2},"a":{"a":0,"k":[0,0],"ix":1},"s":{"a":0,"k":[100,100],"ix":3},"r":{"a":0,"k":0,"ix":6},"o":{"a":0,"k":100,"ix":7},"sk":{"a":0,"k":0,"ix":4},"sa":{"a":0,"k":0,"ix":5},"nm":"Transform"}],"nm":"Group 32","np":5,"cix":2,"bm":0,"ix":32,"mn":"ADBE Vector Group","hd":false},{"ty":"gr","it":[{"ind":0,"ty":"sh","ix":1,"ks":{"a":0,"k":{"i":[[-24.612,0],[0,0],[0,-24.612],[24.612,0],[0,0],[0,24.612]],"o":[[0,0],[24.612,0],[0,24.612],[0,0],[-24.612,0],[0,-24.612]],"v":[[-642.547,-44.564],[642.547,-44.564],[687.111,0],[642.547,44.564],[-642.547,44.564],[-687.111,0]],"c":true},"ix":2},"nm":"Path 1","mn":"ADBE Vector Shape - Group","hd":false},{"ty":"fl","c":{"a":0,"k":[0.850980451995,0.850980451995,0.850980451995,1],"ix":4},"o":{"a":0,"k":69.804,"ix":5},"r":1,"bm":0,"nm":"Fill 1","mn":"ADBE Vector Graphic - Fill","hd":false},{"ty":"tr","p":{"a":0,"k":[691.627,958.952],"ix":2},"a":{"a":0,"k":[0,0],"ix":1},"s":{"a":0,"k":[100,100],"ix":3},"r":{"a":0,"k":0,"ix":6},"o":{"a":0,"k":100,"ix":7},"sk":{"a":0,"k":0,"ix":4},"sa":{"a":0,"k":0,"ix":5},"nm":"Transform"}],"nm":"Group 33","np":2,"cix":2,"bm":0,"ix":33,"mn":"ADBE Vector Group","hd":false}],"ip":0,"op":210,"st":0,"bm":0}]},{"id":"comp_1","nm":"Left eye","fr":30,"layers":[{"ddd":0,"ind":1,"ty":4,"nm":"tingu Outlines","td":1,"sr":1,"ks":{"o":{"a":0,"k":100,"ix":11},"r":{"a":0,"k":0,"ix":10},"p":{"a":0,"k":[748.371,553.769,0],"ix":2,"l":2},"a":{"a":0,"k":[689.369,501.758,0],"ix":1,"l":2},"s":{"a":0,"k":[100,100,100],"ix":6,"l":2}},"ao":0,"shapes":[{"ty":"gr","it":[{"ind":0,"ty":"sh","ix":1,"ks":{"a":0,"k":{"i":[[0,0],[-54.609,74.677],[0,0]],"o":[[0,0],[54.612,-74.676],[0,0]],"v":[[-84.031,80.612],[29.42,24.049],[47.115,-98.725]],"c":false},"ix":2},"nm":"Path 1","mn":"ADBE Vector Shape - Group","hd":false},{"ty":"st","c":{"a":0,"k":[1,0.36862745098,0.16862745098,1],"ix":3},"o":{"a":0,"k":100,"ix":4},"w":{"a":0,"k":163.25,"ix":5},"lc":2,"lj":1,"ml":4,"bm":0,"nm":"Stroke 1","mn":"ADBE Vector Graphic - Stroke","hd":false},{"ty":"tr","p":{"a":0,"k":[733.41,596.422],"ix":2},"a":{"a":0,"k":[0,0],"ix":1},"s":{"a":0,"k":[100,100],"ix":3},"r":{"a":0,"k":0,"ix":6},"o":{"a":0,"k":100,"ix":7},"sk":{"a":0,"k":0,"ix":4},"sa":{"a":0,"k":0,"ix":5},"nm":"Transform"}],"nm":"Group 1","np":2,"cix":2,"bm":0,"ix":1,"mn":"ADBE Vector Group","hd":false},{"ty":"gr","it":[{"ind":0,"ty":"sh","ix":1,"ks":{"a":0,"k":{"i":[[0,0],[0,0],[5.14,45.713],[5.989,13.041],[2.661,4.305],[1.124,1.621],[0.496,0.677],[0.23,0.309],[0.109,0.146],[0.054,0.07],[0.014,0.019],[71.813,-55.111],[0.041,0.052],[0.027,0.032],[0.051,0.067],[0.097,0.13],[0.179,0.247],[0.306,0.439],[0.431,0.696],[0.39,0.846],[0.032,0.304],[15.022,-20.542]],"o":[[0,0],[39.587,-54.135],[-2.436,-21.663],[-2.996,-6.519],[-1.333,-2.16],[-0.564,-0.813],[-0.249,-0.339],[-0.114,-0.152],[-0.057,-0.073],[-0.025,-0.035],[-0.04,-0.051],[-71.809,55.11],[-0.013,-0.016],[-0.052,-0.068],[-0.101,-0.133],[-0.195,-0.26],[-0.361,-0.493],[-0.61,-0.881],[-0.856,-1.385],[-0.775,-1.685],[-0.339,-2.997],[0,0]],"v":[[45.125,14.138],[118.195,67.571],[164.407,-85.368],[149.994,-137.74],[141.31,-154],[137.601,-159.672],[136.01,-161.906],[135.292,-162.876],[134.956,-163.323],[134.791,-163.537],[134.712,-163.643],[62.821,-108.635],[-9.067,-53.629],[-9.145,-53.729],[-9.297,-53.932],[-9.595,-54.325],[-10.156,-55.083],[-11.153,-56.482],[-12.706,-58.845],[-14.521,-62.169],[-15.499,-65.134],[-27.942,-39.292]],"c":true},"ix":2},"nm":"Path 1","mn":"ADBE Vector Shape - Group","hd":false},{"ind":1,"ty":"sh","ix":2,"ks":{"a":0,"k":{"i":[[26.633,-86.512],[-0.063,-0.019],[-0.041,-0.014],[-0.084,-0.024],[-0.179,-0.055],[-0.396,-0.111],[-0.935,-0.241],[-2.441,-0.496],[-7.042,-0.586],[-20.991,4.682],[-39.585,54.13],[0,0],[0,0],[3.571,-2.382],[0.357,-0.081],[-1.339,-0.111],[-1.441,-0.292],[-0.981,-0.252],[-0.561,-0.16],[-0.3,-0.087],[-0.154,-0.049],[-0.078,-0.025],[-0.019,-0.005]],"o":[[-26.632,86.512],[0.019,0.005],[0.081,0.024],[0.171,0.052],[0.357,0.105],[0.788,0.222],[1.867,0.479],[4.869,0.994],[14.076,1.176],[44.066,-9.836],[0,0],[0,0],[-7.969,10.898],[-3.514,2.346],[-0.548,0.122],[0.672,0.055],[0.724,0.147],[0.49,0.127],[0.282,0.079],[0.149,0.046],[0.079,0.022],[0.041,0.011],[0.059,0.019]],"v":[[-68.326,70.701],[-94.836,157.251],[-94.714,157.289],[-94.465,157.365],[-93.942,157.522],[-92.815,157.847],[-90.23,158.547],[-83.757,160.031],[-65.803,162.57],[-12.362,158.771],[118.195,67.571],[45.125,14.138],[-27.942,-39.292],[-45.874,-20.82],[-51.794,-17.922],[-50.751,-17.841],[-47.622,-17.364],[-45.072,-16.773],[-43.495,-16.344],[-42.623,-16.093],[-42.165,-15.955],[-41.932,-15.883],[-41.812,-15.849]],"c":true},"ix":2},"nm":"Path 2","mn":"ADBE Vector Shape - Group","hd":false},{"ind":2,"ty":"sh","ix":3,"ks":{"a":0,"k":{"i":[[0,0],[14.708,-47.778],[-47.781,-14.708],[0,0]],"o":[[-47.778,-14.708],[-14.71,47.781],[0,0],[0,0]],"v":[[-41.693,-15.81],[-154.838,44.068],[-94.958,157.214],[-68.326,70.701]],"c":true},"ix":2},"nm":"Path 3","mn":"ADBE Vector Shape - Group","hd":false},{"ty":"mm","mm":1,"nm":"Merge Paths 1","mn":"ADBE Vector Filter - Merge","hd":false},{"ty":"fl","c":{"a":0,"k":[0.901960844152,0.333333333333,0.149019607843,1],"ix":4},"o":{"a":0,"k":100,"ix":5},"r":1,"bm":0,"nm":"Fill 1","mn":"ADBE Vector Graphic - Fill","hd":false},{"ty":"tr","p":{"a":0,"k":[717.703,606.332],"ix":2},"a":{"a":0,"k":[0,0],"ix":1},"s":{"a":0,"k":[100,100],"ix":3},"r":{"a":0,"k":0,"ix":6},"o":{"a":0,"k":100,"ix":7},"sk":{"a":0,"k":0,"ix":4},"sa":{"a":0,"k":0,"ix":5},"nm":"Transform"}],"nm":"Group 2","np":5,"cix":2,"bm":0,"ix":2,"mn":"ADBE Vector Group","hd":false},{"ty":"gr","it":[{"ind":0,"ty":"sh","ix":1,"ks":{"a":0,"k":{"i":[[-10.475,0],[0,0],[0,-10.475],[10.475,0],[0,0],[0,10.475]],"o":[[0,0],[10.475,0],[0,10.475],[0,0],[-10.475,0],[0,-10.475]],"v":[[-307.539,-18.967],[307.539,-18.967],[326.506,0],[307.539,18.967],[-307.539,18.967],[-326.506,0]],"c":true},"ix":2},"nm":"Path 1","mn":"ADBE Vector Shape - Group","hd":false},{"ty":"fl","c":{"a":0,"k":[0.039215686275,0.478431402468,0.792156922583,1],"ix":4},"o":{"a":0,"k":100,"ix":5},"r":1,"bm":0,"nm":"Fill 1","mn":"ADBE Vector Graphic - Fill","hd":false},{"ty":"tr","p":{"a":0,"k":[1040.936,702.679],"ix":2},"a":{"a":0,"k":[0,0],"ix":1},"s":{"a":0,"k":[100,100],"ix":3},"r":{"a":0,"k":0,"ix":6},"o":{"a":0,"k":100,"ix":7},"sk":{"a":0,"k":0,"ix":4},"sa":{"a":0,"k":0,"ix":5},"nm":"Transform"}],"nm":"Group 3","np":2,"cix":2,"bm":0,"ix":3,"mn":"ADBE Vector Group","hd":false},{"ty":"gr","it":[{"ind":0,"ty":"sh","ix":1,"ks":{"a":0,"k":{"i":[[-10.475,0],[0,0],[0,-10.475],[10.476,0],[0,0],[0,10.475]],"o":[[0,0],[10.476,0],[0,10.475],[0,0],[-10.475,0],[0,-10.475]],"v":[[-365.795,-18.967],[365.795,-18.967],[384.762,0],[365.795,18.967],[-365.795,18.967],[-384.762,0]],"c":true},"ix":2},"nm":"Path 1","mn":"ADBE Vector Shape - Group","hd":false},{"ty":"fl","c":{"a":0,"k":[0.039215686275,0.478431402468,0.792156922583,1],"ix":4},"o":{"a":0,"k":100,"ix":5},"r":1,"bm":0,"nm":"Fill 1","mn":"ADBE Vector Graphic - Fill","hd":false},{"ty":"tr","p":{"a":0,"k":[413.665,702.679],"ix":2},"a":{"a":0,"k":[0,0],"ix":1},"s":{"a":0,"k":[100,100],"ix":3},"r":{"a":0,"k":0,"ix":6},"o":{"a":0,"k":100,"ix":7},"sk":{"a":0,"k":0,"ix":4},"sa":{"a":0,"k":0,"ix":5},"nm":"Transform"}],"nm":"Group 4","np":2,"cix":2,"bm":0,"ix":4,"mn":"ADBE Vector Group","hd":false},{"ty":"gr","it":[{"ind":0,"ty":"sh","ix":1,"ks":{"a":0,"k":{"i":[[0,0],[0,0],[0,0],[0,0]],"o":[[0,0],[0,0],[0,0],[0,0]],"v":[[-375.279,-18.967],[375.279,-18.967],[375.279,18.967],[-375.279,18.967]],"c":true},"ix":2},"nm":"Path 1","mn":"ADBE Vector Shape - Group","hd":false},{"ty":"fl","c":{"a":0,"k":[0,0.396078461292,0.717647058824,1],"ix":4},"o":{"a":0,"k":100,"ix":5},"r":1,"bm":0,"nm":"Fill 1","mn":"ADBE Vector Graphic - Fill","hd":false},{"ty":"tr","p":{"a":0,"k":[959.649,716.228],"ix":2},"a":{"a":0,"k":[0,0],"ix":1},"s":{"a":0,"k":[100,100],"ix":3},"r":{"a":0,"k":0,"ix":6},"o":{"a":0,"k":100,"ix":7},"sk":{"a":0,"k":0,"ix":4},"sa":{"a":0,"k":0,"ix":5},"nm":"Transform"}],"nm":"Group 5","np":2,"cix":2,"bm":0,"ix":5,"mn":"ADBE Vector Group","hd":false},{"ty":"gr","it":[{"ind":0,"ty":"sh","ix":1,"ks":{"a":0,"k":{"i":[[0,0],[0,0],[0,0],[0,0]],"o":[[0,0],[0,0],[0,0],[0,0]],"v":[[-375.279,-18.967],[375.279,-18.967],[375.279,18.967],[-375.279,18.967]],"c":true},"ix":2},"nm":"Path 1","mn":"ADBE Vector Shape - Group","hd":false},{"ty":"fl","c":{"a":0,"k":[0.023529413635,0.423529441684,0.745098039216,1],"ix":4},"o":{"a":0,"k":100,"ix":5},"r":1,"bm":0,"nm":"Fill 1","mn":"ADBE Vector Graphic - Fill","hd":false},{"ty":"tr","p":{"a":0,"k":[423.149,716.228],"ix":2},"a":{"a":0,"k":[0,0],"ix":1},"s":{"a":0,"k":[100,100],"ix":3},"r":{"a":0,"k":0,"ix":6},"o":{"a":0,"k":100,"ix":7},"sk":{"a":0,"k":0,"ix":4},"sa":{"a":0,"k":0,"ix":5},"nm":"Transform"}],"nm":"Group 6","np":2,"cix":2,"bm":0,"ix":6,"mn":"ADBE Vector Group","hd":false},{"ty":"gr","it":[{"ind":0,"ty":"sh","ix":1,"ks":{"a":0,"k":{"i":[[0,0],[-14.965,0],[0,0],[0,-14.965],[0,0],[0,0],[0,14.965]],"o":[[0,-14.965],[0,0],[14.965,0],[0,0],[0,0],[-14.965,0],[0,0]],"v":[[-366.519,-110.688],[-339.423,-137.784],[339.424,-137.784],[366.519,-110.688],[366.519,137.784],[-339.423,137.784],[-366.519,110.689]],"c":true},"ix":2},"nm":"Path 1","mn":"ADBE Vector Shape - Group","hd":false},{"ty":"fl","c":{"a":0,"k":[0.039215686275,0.478431402468,0.792156922583,1],"ix":4},"o":{"a":0,"k":100,"ix":5},"r":1,"bm":0,"nm":"Fill 1","mn":"ADBE Vector Graphic - Fill","hd":false},{"ty":"tr","p":{"a":0,"k":[413.775,821.18],"ix":2},"a":{"a":0,"k":[0,0],"ix":1},"s":{"a":0,"k":[100,100],"ix":3},"r":{"a":0,"k":0,"ix":6},"o":{"a":0,"k":100,"ix":7},"sk":{"a":0,"k":0,"ix":4},"sa":{"a":0,"k":0,"ix":5},"nm":"Transform"}],"nm":"Group 7","np":2,"cix":2,"bm":0,"ix":7,"mn":"ADBE Vector Group","hd":false},{"ty":"gr","it":[{"ind":0,"ty":"sh","ix":1,"ks":{"a":0,"k":{"i":[[-14.965,0],[0,0],[0,-14.965],[0,0],[14.965,0],[0,0],[0,14.965],[0,0]],"o":[[0,0],[14.965,0],[0,0],[0,14.965],[0,0],[-14.965,0],[0,0],[0,-14.965]],"v":[[-617.268,-137.784],[617.268,-137.784],[644.365,-110.688],[644.365,110.688],[617.268,137.784],[-617.268,137.784],[-644.365,110.688],[-644.365,-110.688]],"c":true},"ix":2},"nm":"Path 1","mn":"ADBE Vector Shape - Group","hd":false},{"ty":"fl","c":{"a":0,"k":[0.023529413635,0.423529441684,0.745098039216,1],"ix":4},"o":{"a":0,"k":100,"ix":5},"r":1,"bm":0,"nm":"Fill 1","mn":"ADBE Vector Graphic - Fill","hd":false},{"ty":"tr","p":{"a":0,"k":[691.62,821.179],"ix":2},"a":{"a":0,"k":[0,0],"ix":1},"s":{"a":0,"k":[100,100],"ix":3},"r":{"a":0,"k":0,"ix":6},"o":{"a":0,"k":100,"ix":7},"sk":{"a":0,"k":0,"ix":4},"sa":{"a":0,"k":0,"ix":5},"nm":"Transform"}],"nm":"Group 8","np":2,"cix":2,"bm":0,"ix":8,"mn":"ADBE Vector Group","hd":false},{"ty":"gr","it":[{"ind":0,"ty":"sh","ix":1,"ks":{"a":0,"k":{"i":[[-24.623,0],[0,0],[0,-24.623],[24.624,0],[0,0],[0,24.624]],"o":[[0,0],[24.624,0],[0,24.624],[0,0],[-24.623,0],[0,-24.623]],"v":[[-46.236,-44.585],[46.237,-44.585],[90.821,-0.001],[46.237,44.584],[-46.236,44.584],[-90.821,-0.001]],"c":true},"ix":2},"nm":"Path 1","mn":"ADBE Vector Shape - Group","hd":false},{"ty":"fl","c":{"a":0,"k":[1,0.36862745098,0.16862745098,1],"ix":4},"o":{"a":0,"k":100,"ix":5},"r":1,"bm":0,"nm":"Fill 1","mn":"ADBE Vector Graphic - Fill","hd":false},{"ty":"tr","p":{"a":0,"k":[422.437,895.763],"ix":2},"a":{"a":0,"k":[0,0],"ix":1},"s":{"a":0,"k":[100,100],"ix":3},"r":{"a":0,"k":0,"ix":6},"o":{"a":0,"k":100,"ix":7},"sk":{"a":0,"k":0,"ix":4},"sa":{"a":0,"k":0,"ix":5},"nm":"Transform"}],"nm":"Group 9","np":2,"cix":2,"bm":0,"ix":9,"mn":"ADBE Vector Group","hd":false},{"ty":"gr","it":[{"ind":0,"ty":"sh","ix":1,"ks":{"a":0,"k":{"i":[[-24.623,0],[0,0],[0,-24.623],[24.624,0],[0,0],[0,24.624]],"o":[[0,0],[24.624,0],[0,24.624],[0,0],[-24.623,0],[0,-24.623]],"v":[[-46.237,-44.585],[46.236,-44.585],[90.821,-0.001],[46.236,44.584],[-46.237,44.584],[-90.821,-0.001]],"c":true},"ix":2},"nm":"Path 1","mn":"ADBE Vector Shape - Group","hd":false},{"ty":"fl","c":{"a":0,"k":[1,0.36862745098,0.16862745098,1],"ix":4},"o":{"a":0,"k":100,"ix":5},"r":1,"bm":0,"nm":"Fill 1","mn":"ADBE Vector Graphic - Fill","hd":false},{"ty":"tr","p":{"a":0,"k":[654.446,895.763],"ix":2},"a":{"a":0,"k":[0,0],"ix":1},"s":{"a":0,"k":[100,100],"ix":3},"r":{"a":0,"k":0,"ix":6},"o":{"a":0,"k":100,"ix":7},"sk":{"a":0,"k":0,"ix":4},"sa":{"a":0,"k":0,"ix":5},"nm":"Transform"}],"nm":"Group 10","np":2,"cix":2,"bm":0,"ix":10,"mn":"ADBE Vector Group","hd":false},{"ty":"gr","it":[{"ind":0,"ty":"sh","ix":1,"ks":{"a":0,"k":{"i":[[82.009,39.536],[0,0],[0,0]],"o":[[-82.011,-39.533],[0,0],[0,0]],"v":[[21.627,-50.989],[-126.008,-57.386],[126.008,90.522]],"c":true},"ix":2},"nm":"Path 1","mn":"ADBE Vector Shape - Group","hd":false},{"ty":"fl","c":{"a":0,"k":[1,0.36862745098,0.16862745098,1],"ix":4},"o":{"a":0,"k":100,"ix":5},"r":1,"bm":0,"nm":"Fill 1","mn":"ADBE Vector Graphic - Fill","hd":false},{"ty":"tr","p":{"a":0,"k":[695.229,175.406],"ix":2},"a":{"a":0,"k":[0,0],"ix":1},"s":{"a":0,"k":[100,100],"ix":3},"r":{"a":0,"k":0,"ix":6},"o":{"a":0,"k":100,"ix":7},"sk":{"a":0,"k":0,"ix":4},"sa":{"a":0,"k":0,"ix":5},"nm":"Transform"}],"nm":"Group 11","np":2,"cix":2,"bm":0,"ix":11,"mn":"ADBE Vector Group","hd":false},{"ty":"gr","it":[{"ind":0,"ty":"sh","ix":1,"ks":{"a":0,"k":{"i":[[0,0],[-0.149,-28.806],[0,0],[47.136,32.643],[0,0]],"o":[[24.88,-14.521],[0,0],[0,0],[-47.139,-32.642],[0,0]],"v":[[36.98,-84.81],[93.28,-52.678],[94.079,99.331],[17.831,49.835],[-94.078,-8.318]],"c":true},"ix":2},"nm":"Path 1","mn":"ADBE Vector Shape - Group","hd":false},{"ty":"fl","c":{"a":0,"k":[0.996078491211,0.611764705882,0.36862745098,1],"ix":4},"o":{"a":0,"k":100,"ix":5},"r":1,"bm":0,"nm":"Fill 1","mn":"ADBE Vector Graphic - Fill","hd":false},{"ty":"tr","p":{"a":0,"k":[708.053,123.382],"ix":2},"a":{"a":0,"k":[0,0],"ix":1},"s":{"a":0,"k":[100,100],"ix":3},"r":{"a":0,"k":0,"ix":6},"o":{"a":0,"k":100,"ix":7},"sk":{"a":0,"k":0,"ix":4},"sa":{"a":0,"k":0,"ix":5},"nm":"Transform"}],"nm":"Group 12","np":2,"cix":2,"bm":0,"ix":12,"mn":"ADBE Vector Group","hd":false},{"ty":"gr","it":[{"ind":0,"ty":"sh","ix":1,"ks":{"a":0,"k":{"i":[[0,0],[-0.068,-44.966],[0,0],[0,0]],"o":[[38.918,-22.522],[0,0],[0,0],[0,0]],"v":[[33.991,-104.072],[121.687,-53.589],[121.966,126.594],[-121.965,-13.826]],"c":true},"ix":2},"nm":"Path 1","mn":"ADBE Vector Shape - Group","hd":false},{"ty":"fl","c":{"a":0,"k":[1,0.36862745098,0.16862745098,1],"ix":4},"o":{"a":0,"k":100,"ix":5},"r":1,"bm":0,"nm":"Fill 1","mn":"ADBE Vector Graphic - Fill","hd":false},{"ty":"tr","p":{"a":0,"k":[698.524,127.494],"ix":2},"a":{"a":0,"k":[0,0],"ix":1},"s":{"a":0,"k":[100,100],"ix":3},"r":{"a":0,"k":0,"ix":6},"o":{"a":0,"k":100,"ix":7},"sk":{"a":0,"k":0,"ix":4},"sa":{"a":0,"k":0,"ix":5},"nm":"Transform"}],"nm":"Group 13","np":2,"cix":2,"bm":0,"ix":13,"mn":"ADBE Vector Group","hd":false},{"ty":"gr","it":[{"ind":0,"ty":"sh","ix":1,"ks":{"a":0,"k":{"i":[[0,0],[-2.729,2.978],[0,0],[6.162,0],[0,0],[-4.309,-4.702]],"o":[[2.731,2.978],[0,0],[4.308,-4.702],[0,0],[-6.159,0],[0,0]],"v":[[-4.976,12.85],[4.974,12.85],[19.695,-3.212],[14.72,-15.828],[-14.722,-15.828],[-19.694,-3.212]],"c":true},"ix":2},"nm":"Path 1","mn":"ADBE Vector Shape - Group","hd":false},{"ty":"fl","c":{"a":0,"k":[0.839215746113,0.235294132607,0,1],"ix":4},"o":{"a":0,"k":100,"ix":5},"r":1,"bm":0,"nm":"Fill 1","mn":"ADBE Vector Graphic - Fill","hd":false},{"ty":"tr","p":{"a":0,"k":[451.028,333.629],"ix":2},"a":{"a":0,"k":[0,0],"ix":1},"s":{"a":0,"k":[100,100],"ix":3},"r":{"a":0,"k":0,"ix":6},"o":{"a":0,"k":100,"ix":7},"sk":{"a":0,"k":0,"ix":4},"sa":{"a":0,"k":0,"ix":5},"nm":"Transform"}],"nm":"Group 14","np":2,"cix":2,"bm":0,"ix":14,"mn":"ADBE Vector Group","hd":false},{"ty":"gr","it":[{"ind":0,"ty":"sh","ix":1,"ks":{"a":0,"k":{"i":[[0,26.283],[26.283,0],[0,0],[0,-26.283],[-26.283,0],[0,0]],"o":[[0,-26.283],[0,0],[-26.283,0],[0,26.283],[0,0],[26.283,0]],"v":[[74.006,-0.001],[26.417,-47.59],[-26.414,-47.59],[-74.006,-0.001],[-26.414,47.59],[26.417,47.59]],"c":true},"ix":2},"nm":"Path 1","mn":"ADBE Vector Shape - Group","hd":false},{"ty":"fl","c":{"a":0,"k":[0.996078491211,0.611764705882,0.36862745098,1],"ix":4},"o":{"a":0,"k":100,"ix":5},"r":1,"bm":0,"nm":"Fill 1","mn":"ADBE Vector Graphic - Fill","hd":false},{"ty":"tr","p":{"a":0,"k":[437.23,376.399],"ix":2},"a":{"a":0,"k":[0,0],"ix":1},"s":{"a":0,"k":[100,100],"ix":3},"r":{"a":0,"k":0,"ix":6},"o":{"a":0,"k":100,"ix":7},"sk":{"a":0,"k":0,"ix":4},"sa":{"a":0,"k":0,"ix":5},"nm":"Transform"}],"nm":"Group 15","np":2,"cix":2,"bm":0,"ix":15,"mn":"ADBE Vector Group","hd":false},{"ty":"gr","it":[{"ind":0,"ty":"sh","ix":1,"ks":{"a":0,"k":{"i":[[0,26.283],[-26.285,0],[0,0],[0,-26.283],[26.283,0],[0,0]],"o":[[0,-26.283],[0,0],[26.283,0],[0,26.283],[0,0],[-26.283,0]],"v":[[-74.006,-0.001],[-26.415,-47.59],[26.417,-47.59],[74.006,-0.001],[26.417,47.59],[-26.415,47.59]],"c":true},"ix":2},"nm":"Path 1","mn":"ADBE Vector Shape - Group","hd":false},{"ty":"fl","c":{"a":0,"k":[0.996078491211,0.611764705882,0.36862745098,1],"ix":4},"o":{"a":0,"k":100,"ix":5},"r":1,"bm":0,"nm":"Fill 1","mn":"ADBE Vector Graphic - Fill","hd":false},{"ty":"tr","p":{"a":0,"k":[464.825,376.399],"ix":2},"a":{"a":0,"k":[0,0],"ix":1},"s":{"a":0,"k":[100,100],"ix":3},"r":{"a":0,"k":0,"ix":6},"o":{"a":0,"k":100,"ix":7},"sk":{"a":0,"k":0,"ix":4},"sa":{"a":0,"k":0,"ix":5},"nm":"Transform"}],"nm":"Group 16","np":2,"cix":2,"bm":0,"ix":16,"mn":"ADBE Vector Group","hd":false},{"ty":"gr","it":[{"ind":0,"ty":"sh","ix":1,"ks":{"a":0,"k":{"i":[[4.427,-1.186],[0,0],[1.186,4.426],[-4.426,1.186],[0,0],[-1.186,-4.426]],"o":[[0,0],[-4.427,1.186],[-1.186,-4.427],[0,0],[4.426,-1.186],[1.187,4.427]],"v":[[25.048,1.879],[-20.753,14.151],[-30.916,8.284],[-25.049,-1.879],[20.753,-14.151],[30.915,-8.284]],"c":true},"ix":2},"nm":"Path 1","mn":"ADBE Vector Shape - Group","hd":false},{"ty":"fl","c":{"a":0,"k":[0.901960844152,0.333333333333,0.149019607843,1],"ix":4},"o":{"a":0,"k":100,"ix":5},"r":1,"bm":0,"nm":"Fill 1","mn":"ADBE Vector Graphic - Fill","hd":false},{"ty":"tr","p":{"a":0,"k":[271.086,387.608],"ix":2},"a":{"a":0,"k":[0,0],"ix":1},"s":{"a":0,"k":[100,100],"ix":3},"r":{"a":0,"k":0,"ix":6},"o":{"a":0,"k":100,"ix":7},"sk":{"a":0,"k":0,"ix":4},"sa":{"a":0,"k":0,"ix":5},"nm":"Transform"}],"nm":"Group 17","np":2,"cix":2,"bm":0,"ix":17,"mn":"ADBE Vector Group","hd":false},{"ty":"gr","it":[{"ind":0,"ty":"sh","ix":1,"ks":{"a":0,"k":{"i":[[4.427,1.186],[0,0],[1.186,-4.426],[-4.426,-1.186],[0,0],[-1.186,4.426]],"o":[[0,0],[-4.427,-1.186],[-1.186,4.427],[0,0],[4.426,1.186],[1.187,-4.427]],"v":[[25.048,-1.879],[-20.753,-14.151],[-30.916,-8.284],[-25.049,1.879],[20.753,14.151],[30.915,8.284]],"c":true},"ix":2},"nm":"Path 1","mn":"ADBE Vector Shape - Group","hd":false},{"ty":"fl","c":{"a":0,"k":[0.901960844152,0.333333333333,0.149019607843,1],"ix":4},"o":{"a":0,"k":100,"ix":5},"r":1,"bm":0,"nm":"Fill 1","mn":"ADBE Vector Graphic - Fill","hd":false},{"ty":"tr","p":{"a":0,"k":[271.086,325.715],"ix":2},"a":{"a":0,"k":[0,0],"ix":1},"s":{"a":0,"k":[100,100],"ix":3},"r":{"a":0,"k":0,"ix":6},"o":{"a":0,"k":100,"ix":7},"sk":{"a":0,"k":0,"ix":4},"sa":{"a":0,"k":0,"ix":5},"nm":"Transform"}],"nm":"Group 18","np":2,"cix":2,"bm":0,"ix":18,"mn":"ADBE Vector Group","hd":false},{"ty":"gr","it":[{"ind":0,"ty":"sh","ix":1,"ks":{"a":0,"k":{"i":[[4.583,0],[0,0],[0,-4.583],[-4.583,0],[0,0],[0,4.583]],"o":[[0,0],[-4.583,0],[0,4.583],[0,0],[4.583,0],[0,-4.583]],"v":[[23.709,-8.298],[-23.708,-8.298],[-32.006,0],[-23.708,8.298],[23.709,8.298],[32.007,0]],"c":true},"ix":2},"nm":"Path 1","mn":"ADBE Vector Shape - Group","hd":false},{"ty":"fl","c":{"a":0,"k":[0.901960844152,0.333333333333,0.149019607843,1],"ix":4},"o":{"a":0,"k":100,"ix":5},"r":1,"bm":0,"nm":"Fill 1","mn":"ADBE Vector Graphic - Fill","hd":false},{"ty":"tr","p":{"a":0,"k":[255.725,356.538],"ix":2},"a":{"a":0,"k":[0,0],"ix":1},"s":{"a":0,"k":[100,100],"ix":3},"r":{"a":0,"k":0,"ix":6},"o":{"a":0,"k":100,"ix":7},"sk":{"a":0,"k":0,"ix":4},"sa":{"a":0,"k":0,"ix":5},"nm":"Transform"}],"nm":"Group 19","np":2,"cix":2,"bm":0,"ix":19,"mn":"ADBE Vector Group","hd":false},{"ty":"gr","it":[{"ind":0,"ty":"sh","ix":1,"ks":{"a":0,"k":{"i":[[-4.427,-1.186],[0,0],[-1.186,4.426],[4.426,1.186],[0,0],[1.186,-4.426]],"o":[[0,0],[4.427,1.186],[1.186,-4.427],[0,0],[-4.426,-1.186],[-1.187,4.427]],"v":[[-25.048,1.879],[20.753,14.151],[30.916,8.284],[25.049,-1.879],[-20.753,-14.151],[-30.915,-8.284]],"c":true},"ix":2},"nm":"Path 1","mn":"ADBE Vector Shape - Group","hd":false},{"ty":"fl","c":{"a":0,"k":[0.901960844152,0.333333333333,0.149019607843,1],"ix":4},"o":{"a":0,"k":100,"ix":5},"r":1,"bm":0,"nm":"Fill 1","mn":"ADBE Vector Graphic - Fill","hd":false},{"ty":"tr","p":{"a":0,"k":[646.984,387.608],"ix":2},"a":{"a":0,"k":[0,0],"ix":1},"s":{"a":0,"k":[100,100],"ix":3},"r":{"a":0,"k":0,"ix":6},"o":{"a":0,"k":100,"ix":7},"sk":{"a":0,"k":0,"ix":4},"sa":{"a":0,"k":0,"ix":5},"nm":"Transform"}],"nm":"Group 20","np":2,"cix":2,"bm":0,"ix":20,"mn":"ADBE Vector Group","hd":false},{"ty":"gr","it":[{"ind":0,"ty":"sh","ix":1,"ks":{"a":0,"k":{"i":[[-4.427,1.186],[0,0],[-1.186,-4.426],[4.426,-1.186],[0,0],[1.186,4.426]],"o":[[0,0],[4.427,-1.186],[1.186,4.427],[0,0],[-4.426,1.186],[-1.187,-4.427]],"v":[[-25.048,-1.879],[20.753,-14.151],[30.916,-8.284],[25.049,1.879],[-20.753,14.151],[-30.915,8.284]],"c":true},"ix":2},"nm":"Path 1","mn":"ADBE Vector Shape - Group","hd":false},{"ty":"fl","c":{"a":0,"k":[0.901960844152,0.333333333333,0.149019607843,1],"ix":4},"o":{"a":0,"k":100,"ix":5},"r":1,"bm":0,"nm":"Fill 1","mn":"ADBE Vector Graphic - Fill","hd":false},{"ty":"tr","p":{"a":0,"k":[646.984,325.715],"ix":2},"a":{"a":0,"k":[0,0],"ix":1},"s":{"a":0,"k":[100,100],"ix":3},"r":{"a":0,"k":0,"ix":6},"o":{"a":0,"k":100,"ix":7},"sk":{"a":0,"k":0,"ix":4},"sa":{"a":0,"k":0,"ix":5},"nm":"Transform"}],"nm":"Group 21","np":2,"cix":2,"bm":0,"ix":21,"mn":"ADBE Vector Group","hd":false},{"ty":"gr","it":[{"ind":0,"ty":"sh","ix":1,"ks":{"a":0,"k":{"i":[[-4.583,0],[0,0],[0,-4.583],[4.583,0],[0,0],[0,4.583]],"o":[[0,0],[4.583,0],[0,4.583],[0,0],[-4.583,0],[0,-4.583]],"v":[[-23.708,-8.298],[23.708,-8.298],[32.006,0],[23.708,8.298],[-23.708,8.298],[-32.007,0]],"c":true},"ix":2},"nm":"Path 1","mn":"ADBE Vector Shape - Group","hd":false},{"ty":"fl","c":{"a":0,"k":[0.901960844152,0.333333333333,0.149019607843,1],"ix":4},"o":{"a":0,"k":100,"ix":5},"r":1,"bm":0,"nm":"Fill 1","mn":"ADBE Vector Graphic - Fill","hd":false},{"ty":"tr","p":{"a":0,"k":[662.355,356.538],"ix":2},"a":{"a":0,"k":[0,0],"ix":1},"s":{"a":0,"k":[100,100],"ix":3},"r":{"a":0,"k":0,"ix":6},"o":{"a":0,"k":100,"ix":7},"sk":{"a":0,"k":0,"ix":4},"sa":{"a":0,"k":0,"ix":5},"nm":"Transform"}],"nm":"Group 22","np":2,"cix":2,"bm":0,"ix":22,"mn":"ADBE Vector Group","hd":false},{"ty":"gr","it":[{"ind":0,"ty":"sh","ix":1,"ks":{"a":0,"k":{"i":[[-75.239,0],[0,0],[0,-75.239],[0,0],[75.239,0],[0,75.238],[0,0]],"o":[[0,0],[75.239,0],[0,0],[0,75.238],[-75.239,0],[0,0],[0,-75.239]],"v":[[0,-163.475],[0,-163.475],[136.232,-27.243],[136.232,27.244],[0,163.475],[-136.232,27.244],[-136.232,-27.243]],"c":true},"ix":2},"nm":"Path 1","mn":"ADBE Vector Shape - Group","hd":false},{"ty":"fl","c":{"a":0,"k":[0.996078491211,0.611764705882,0.36862745098,1],"ix":4},"o":{"a":0,"k":100,"ix":5},"r":1,"bm":0,"nm":"Fill 1","mn":"ADBE Vector Graphic - Fill","hd":false},{"ty":"tr","p":{"a":0,"k":[452.425,634.866],"ix":2},"a":{"a":0,"k":[0,0],"ix":1},"s":{"a":0,"k":[100,100],"ix":3},"r":{"a":0,"k":0,"ix":6},"o":{"a":0,"k":100,"ix":7},"sk":{"a":0,"k":0,"ix":4},"sa":{"a":0,"k":0,"ix":5},"nm":"Transform"}],"nm":"Group 23","np":2,"cix":2,"bm":0,"ix":23,"mn":"ADBE Vector Group","hd":false},{"ty":"gr","it":[{"ind":0,"ty":"sh","ix":1,"ks":{"a":0,"k":{"i":[[0,0],[-16.477,-118.903],[0,0],[96.822,0],[0,0],[-11.09,94.814],[0,0],[-121.986,0]],"o":[[120.038,0],[0,0],[13.29,95.903],[0,0],[-95.457,0],[0,0],[14.171,-121.159],[0,0]],"v":[[62.706,-385.734],[300.871,-178.299],[353.89,204.292],[195.858,385.734],[-197.628,385.734],[-356.091,207.658],[-311.539,-173.227],[-72.728,-385.734]],"c":true},"ix":2},"nm":"Path 1","mn":"ADBE Vector Shape - Group","hd":false},{"ty":"st","c":{"a":0,"k":[0.901960844152,0.333333333333,0.149019607843,1],"ix":3},"o":{"a":0,"k":100,"ix":4},"w":{"a":0,"k":7.325,"ix":5},"lc":1,"lj":1,"ml":4,"bm":0,"nm":"Stroke 1","mn":"ADBE Vector Graphic - Stroke","hd":false},{"ty":"fl","c":{"a":0,"k":[1,0.36862745098,0.16862745098,1],"ix":4},"o":{"a":0,"k":100,"ix":5},"r":1,"bm":0,"nm":"Fill 1","mn":"ADBE Vector Graphic - Fill","hd":false},{"ty":"tr","p":{"a":0,"k":[554.111,439.879],"ix":2},"a":{"a":0,"k":[0,0],"ix":1},"s":{"a":0,"k":[100,100],"ix":3},"r":{"a":0,"k":0,"ix":6},"o":{"a":0,"k":100,"ix":7},"sk":{"a":0,"k":0,"ix":4},"sa":{"a":0,"k":0,"ix":5},"nm":"Transform"}],"nm":"Group 24","np":3,"cix":2,"bm":0,"ix":24,"mn":"ADBE Vector Group","hd":false},{"ty":"gr","it":[{"ind":0,"ty":"sh","ix":1,"ks":{"a":0,"k":{"i":[[0,0],[4.837,-41.275],[0,0],[-19.484,12.283],[0,0]],"o":[[-10.183,-40.291],[0,0],[0,0],[19.485,-12.282],[0,0]],"v":[[32.41,-64.541],[-41.059,-59.728],[-60.353,104.832],[4.405,70.862],[60.353,46.026]],"c":true},"ix":2},"nm":"Path 1","mn":"ADBE Vector Shape - Group","hd":false},{"ty":"fl","c":{"a":0,"k":[0.996078491211,0.611764705882,0.36862745098,1],"ix":4},"o":{"a":0,"k":100,"ix":5},"r":1,"bm":0,"nm":"Fill 1","mn":"ADBE Vector Graphic - Fill","hd":false},{"ty":"tr","p":{"a":0,"k":[387.989,143.301],"ix":2},"a":{"a":0,"k":[0,0],"ix":1},"s":{"a":0,"k":[100,100],"ix":3},"r":{"a":0,"k":0,"ix":6},"o":{"a":0,"k":100,"ix":7},"sk":{"a":0,"k":0,"ix":4},"sa":{"a":0,"k":0,"ix":5},"nm":"Transform"}],"nm":"Group 25","np":2,"cix":2,"bm":0,"ix":25,"mn":"ADBE Vector Group","hd":false},{"ty":"gr","it":[{"ind":0,"ty":"sh","ix":1,"ks":{"a":0,"k":{"i":[[0,0],[6.641,-44.473],[0,0],[0,0]],"o":[[-35.208,-27.969],[0,0],[0,0],[0,0]],"v":[[-21.95,-112.022],[-116.085,-74.9],[-148.179,139.99],[148.179,23.123]],"c":true},"ix":2},"nm":"Path 1","mn":"ADBE Vector Shape - Group","hd":false},{"ty":"fl","c":{"a":0,"k":[1,0.36862745098,0.16862745098,1],"ix":4},"o":{"a":0,"k":100,"ix":5},"r":1,"bm":0,"nm":"Fill 1","mn":"ADBE Vector Graphic - Fill","hd":false},{"ty":"tr","p":{"a":0,"k":[450.047,140.241],"ix":2},"a":{"a":0,"k":[0,0],"ix":1},"s":{"a":0,"k":[100,100],"ix":3},"r":{"a":0,"k":0,"ix":6},"o":{"a":0,"k":100,"ix":7},"sk":{"a":0,"k":0,"ix":4},"sa":{"a":0,"k":0,"ix":5},"nm":"Transform"}],"nm":"Group 26","np":2,"cix":2,"bm":0,"ix":26,"mn":"ADBE Vector Group","hd":false},{"ty":"gr","it":[{"ind":0,"ty":"sh","ix":1,"ks":{"a":0,"k":{"i":[[0,0],[-36.875,28.762],[-22.238,47.556],[0,0]],"o":[[0,0],[47.502,-37.054],[27.843,-59.547],[0,0]],"v":[[-102.271,57.109],[3.547,94.163],[18.049,-63.378],[102.271,-107.808]],"c":false},"ix":2},"nm":"Path 1","mn":"ADBE Vector Shape - Group","hd":false},{"ty":"st","c":{"a":0,"k":[1,0.36862745098,0.16862745098,1],"ix":3},"o":{"a":0,"k":100,"ix":4},"w":{"a":0,"k":108.543,"ix":5},"lc":2,"lj":1,"ml":4,"bm":0,"nm":"Stroke 1","mn":"ADBE Vector Graphic - Stroke","hd":false},{"ty":"tr","p":{"a":0,"k":[895.691,583.982],"ix":2},"a":{"a":0,"k":[0,0],"ix":1},"s":{"a":0,"k":[100,100],"ix":3},"r":{"a":0,"k":0,"ix":6},"o":{"a":0,"k":100,"ix":7},"sk":{"a":0,"k":0,"ix":4},"sa":{"a":0,"k":0,"ix":5},"nm":"Transform"}],"nm":"Group 27","np":2,"cix":2,"bm":0,"ix":27,"mn":"ADBE Vector Group","hd":false},{"ty":"gr","it":[{"ind":0,"ty":"sh","ix":1,"ks":{"a":0,"k":{"i":[[0,0],[-56.649,73.14],[0,0]],"o":[[0,0],[56.647,-73.143],[0,0]],"v":[[-51.177,98.907],[-28.218,-25.764],[84.867,-76.745]],"c":false},"ix":2},"nm":"Path 1","mn":"ADBE Vector Shape - Group","hd":false},{"ty":"st","c":{"a":0,"k":[1,0.36862745098,0.16862745098,1],"ix":3},"o":{"a":0,"k":100,"ix":4},"w":{"a":0,"k":163.25,"ix":5},"lc":2,"lj":1,"ml":4,"bm":0,"nm":"Stroke 1","mn":"ADBE Vector Graphic - Stroke","hd":false},{"ty":"tr","p":{"a":0,"k":[248.117,622.052],"ix":2},"a":{"a":0,"k":[0,0],"ix":1},"s":{"a":0,"k":[100,100],"ix":3},"r":{"a":0,"k":0,"ix":6},"o":{"a":0,"k":100,"ix":7},"sk":{"a":0,"k":0,"ix":4},"sa":{"a":0,"k":0,"ix":5},"nm":"Transform"}],"nm":"Group 28","np":2,"cix":2,"bm":0,"ix":28,"mn":"ADBE Vector Group","hd":false},{"ty":"gr","it":[{"ind":0,"ty":"sh","ix":1,"ks":{"a":0,"k":{"i":[[0,0],[0,0],[-45.351,7.712],[-14.188,-2.146],[-4.877,-1.366],[-1.87,-0.631],[-0.792,-0.288],[-0.361,-0.138],[-0.17,-0.065],[-0.082,-0.03],[-0.021,-0.008],[33.087,-84.255],[-0.06,-0.025],[-0.041,-0.017],[-0.079,-0.03],[-0.152,-0.057],[-0.287,-0.106],[-0.51,-0.17],[-0.789,-0.222],[-0.918,-0.141],[-0.301,0.052],[15.583,-20.119]],"o":[[0,0],[41.067,-53.024],[21.492,-3.652],[7.096,1.073],[2.441,0.683],[0.935,0.317],[0.393,0.146],[0.178,0.068],[0.084,0.035],[0.043,0.016],[0.06,0.025],[-33.086,84.255],[0.019,0.008],[0.079,0.03],[0.157,0.059],[0.304,0.114],[0.572,0.208],[1.013,0.345],[1.568,0.439],[1.838,0.277],[2.972,-0.504],[0,0]],"v":[[-10.176,-40.991],[-81.742,-96.418],[52.438,-183.15],[106.752,-183.792],[124.784,-179.947],[131.26,-177.953],[133.848,-177.042],[134.978,-176.62],[135.5,-176.422],[135.75,-176.324],[135.874,-176.276],[102.909,-91.972],[69.942,-7.668],[70.061,-7.622],[70.297,-7.53],[70.76,-7.354],[71.643,-7.023],[73.264,-6.455],[75.963,-5.615],[79.658,-4.791],[82.78,-4.672],[61.39,14.437]],"c":true},"ix":2},"nm":"Path 1","mn":"ADBE Vector Shape - Group","hd":false},{"ind":1,"ty":"sh","ix":2,"ks":{"a":0,"k":{"i":[[75.765,-49.534],[0.035,0.051],[0.023,0.035],[0.048,0.073],[0.101,0.157],[0.217,0.35],[0.49,0.832],[1.153,2.209],[2.514,6.606],[1.307,21.465],[-41.063,53.018],[0,0],[0,0],[1.301,-4.092],[-0.022,-0.363],[0.477,1.255],[0.68,1.304],[0.514,0.873],[0.309,0.496],[0.169,0.263],[0.087,0.135],[0.045,0.07],[0.011,0.016]],"o":[[-75.765,49.534],[-0.012,-0.019],[-0.047,-0.073],[-0.096,-0.149],[-0.2,-0.314],[-0.432,-0.693],[-0.979,-1.664],[-2.302,-4.405],[-5.024,-13.201],[-2.745,-45.066],[0,0],[0,0],[-8.267,10.673],[-1.282,4.026],[0.032,0.561],[-0.241,-0.628],[-0.344,-0.655],[-0.257,-0.436],[-0.154,-0.246],[-0.084,-0.132],[-0.044,-0.068],[-0.022,-0.033],[-0.034,-0.052]],"v":[[-33.135,83.68],[-108.969,133.109],[-109.039,133],[-109.181,132.781],[-109.476,132.323],[-110.101,131.328],[-111.487,129.039],[-114.707,123.229],[-122.116,106.679],[-133.251,54.276],[-81.742,-96.418],[-10.176,-40.991],[61.39,14.437],[48.601,36.78],[47.455,43.269],[47.089,42.291],[45.764,39.416],[44.488,37.129],[43.641,35.731],[43.157,34.964],[42.9,34.561],[42.766,34.355],[42.699,34.252]],"c":true},"ix":2},"nm":"Path 2","mn":"ADBE Vector Shape - Group","hd":false},{"ind":2,"ty":"sh","ix":3,"ks":{"a":0,"k":{"i":[[0,0],[41.843,-27.359],[27.357,41.842],[0,0]],"o":[[27.358,41.844],[-41.844,27.356],[0,0],[0,0]],"v":[[42.63,34.146],[16.399,159.446],[-108.9,133.214],[-33.135,83.68]],"c":true},"ix":2},"nm":"Path 3","mn":"ADBE Vector Shape - Group","hd":false},{"ty":"mm","mm":1,"nm":"Merge Paths 1","mn":"ADBE Vector Filter - Merge","hd":false},{"ty":"fl","c":{"a":0,"k":[0.901960844152,0.333333333333,0.149019607843,1],"ix":4},"o":{"a":0,"k":100,"ix":5},"r":1,"bm":0,"nm":"Fill 1","mn":"ADBE Vector Graphic - Fill","hd":false},{"ty":"tr","p":{"a":0,"k":[230.075,637.278],"ix":2},"a":{"a":0,"k":[0,0],"ix":1},"s":{"a":0,"k":[100,100],"ix":3},"r":{"a":0,"k":0,"ix":6},"o":{"a":0,"k":100,"ix":7},"sk":{"a":0,"k":0,"ix":4},"sa":{"a":0,"k":0,"ix":5},"nm":"Transform"}],"nm":"Group 29","np":5,"cix":2,"bm":0,"ix":29,"mn":"ADBE Vector Group","hd":false},{"ty":"gr","it":[{"ind":0,"ty":"sh","ix":1,"ks":{"a":0,"k":{"i":[[-24.612,0],[0,0],[0,-24.612],[24.612,0],[0,0],[0,24.612]],"o":[[0,0],[24.612,0],[0,24.612],[0,0],[-24.612,0],[0,-24.612]],"v":[[-642.547,-44.564],[642.547,-44.564],[687.111,0],[642.547,44.564],[-642.547,44.564],[-687.111,0]],"c":true},"ix":2},"nm":"Path 1","mn":"ADBE Vector Shape - Group","hd":false},{"ty":"fl","c":{"a":0,"k":[0.850980451995,0.850980451995,0.850980451995,1],"ix":4},"o":{"a":0,"k":69.804,"ix":5},"r":1,"bm":0,"nm":"Fill 1","mn":"ADBE Vector Graphic - Fill","hd":false},{"ty":"tr","p":{"a":0,"k":[691.627,958.952],"ix":2},"a":{"a":0,"k":[0,0],"ix":1},"s":{"a":0,"k":[100,100],"ix":3},"r":{"a":0,"k":0,"ix":6},"o":{"a":0,"k":100,"ix":7},"sk":{"a":0,"k":0,"ix":4},"sa":{"a":0,"k":0,"ix":5},"nm":"Transform"}],"nm":"Group 30","np":2,"cix":2,"bm":0,"ix":30,"mn":"ADBE Vector Group","hd":false}],"ip":0,"op":181,"st":0,"bm":0},{"ddd":0,"ind":2,"ty":4,"nm":"Shape Layer 1","tt":1,"sr":1,"ks":{"o":{"a":0,"k":100,"ix":11},"r":{"a":0,"k":0,"ix":10},"p":{"a":1,"k":[{"i":{"x":0.611,"y":1},"o":{"x":0.988,"y":0},"t":30,"s":[396.642,239.802,0],"to":[0,0,0],"ti":[0,0,0]},{"i":{"x":0,"y":1},"o":{"x":0.167,"y":0},"t":45,"s":[396.642,341.465,0],"to":[0,0,0],"ti":[0,0,0]},{"i":{"x":0.667,"y":0.667},"o":{"x":1,"y":1},"t":60,"s":[396.642,239.802,0],"to":[0,0,0],"ti":[0,0,0]},{"i":{"x":0.667,"y":1},"o":{"x":1,"y":0},"t":120,"s":[396.642,239.802,0],"to":[0,0,0],"ti":[0,0,0]},{"i":{"x":0,"y":1},"o":{"x":0.167,"y":0},"t":135,"s":[396.642,333.037,0],"to":[0,0,0],"ti":[0,0,0]},{"t":150,"s":[396.642,239.802,0]}],"ix":2,"l":2},"a":{"a":0,"k":[-347.858,-206.963,0],"ix":1,"l":2},"s":{"a":0,"k":[100,100,100],"ix":6,"l":2}},"ao":0,"shapes":[{"ty":"gr","it":[{"ty":"rc","d":1,"s":{"a":0,"k":[154.864,94.025],"ix":2},"p":{"a":0,"k":[0,0],"ix":3},"r":{"a":0,"k":0,"ix":4},"nm":"Rectangle Path 1","mn":"ADBE Vector Shape - Rect","hd":false},{"ty":"fl","c":{"a":0,"k":[1,0.368627002192,0.168626987233,1],"ix":4},"o":{"a":0,"k":100,"ix":5},"r":1,"bm":0,"nm":"Fill 1","mn":"ADBE Vector Graphic - Fill","hd":false},{"ty":"tr","p":{"a":0,"k":[-347.858,-206.963],"ix":2},"a":{"a":0,"k":[0,0],"ix":1},"s":{"a":0,"k":[100,100],"ix":3},"r":{"a":0,"k":0,"ix":6},"o":{"a":0,"k":100,"ix":7},"sk":{"a":0,"k":0,"ix":4},"sa":{"a":0,"k":0,"ix":5},"nm":"Transform"}],"nm":"Rectangle 1","np":3,"cix":2,"bm":0,"ix":1,"mn":"ADBE Vector Group","hd":false}],"ip":0,"op":210,"st":0,"bm":0},{"ddd":0,"ind":3,"ty":4,"nm":"eye lid Outlines","sr":1,"ks":{"o":{"a":0,"k":100,"ix":11},"r":{"a":0,"k":0,"ix":10},"p":{"a":0,"k":[397.283,244.542,0],"ix":2,"l":2},"a":{"a":0,"k":[74.764,53.568,0],"ix":1,"l":2},"s":{"a":0,"k":[100,100,100],"ix":6,"l":2}},"ao":0,"shapes":[{"ty":"gr","it":[{"ind":0,"ty":"sh","ix":1,"ks":{"a":0,"k":{"i":[[0,0],[-31.765,0],[0,0],[0,-31.765],[0,0],[0,0]],"o":[[0,-31.765],[0,0],[31.764,0],[0,0],[0,0],[0,0]],"v":[[-74.514,10.096],[-17,-47.418],[17,-47.418],[74.514,10.096],[74.514,47.418],[-74.514,47.418]],"c":true},"ix":2},"nm":"Path 1","mn":"ADBE Vector Shape - Group","hd":false},{"ty":"fl","c":{"a":0,"k":[1,0.36862745098,0.16862745098,1],"ix":4},"o":{"a":0,"k":100,"ix":5},"r":1,"bm":0,"nm":"Fill 1","mn":"ADBE Vector Graphic - Fill","hd":false},{"ty":"tr","p":{"a":0,"k":[74.764,59.469],"ix":2},"a":{"a":0,"k":[0,0],"ix":1},"s":{"a":0,"k":[100,100],"ix":3},"r":{"a":0,"k":0,"ix":6},"o":{"a":0,"k":100,"ix":7},"sk":{"a":0,"k":0,"ix":4},"sa":{"a":0,"k":0,"ix":5},"nm":"Transform"}],"nm":"Group 1","np":2,"cix":2,"bm":0,"ix":1,"mn":"ADBE Vector Group","hd":false},{"ty":"gr","it":[{"ind":0,"ty":"sh","ix":1,"ks":{"a":0,"k":{"i":[[0,0],[-31.765,0],[0,0],[0,-31.765],[0,0],[0,0]],"o":[[0,-31.765],[0,0],[31.764,0],[0,0],[0,0],[0,0]],"v":[[-74.514,10.096],[-17,-47.418],[17,-47.418],[74.514,10.096],[74.514,47.418],[-74.514,47.418]],"c":true},"ix":2},"nm":"Path 1","mn":"ADBE Vector Shape - Group","hd":false},{"ty":"fl","c":{"a":0,"k":[1,0.36862745098,0.16862745098,1],"ix":4},"o":{"a":0,"k":100,"ix":5},"r":1,"bm":0,"nm":"Fill 1","mn":"ADBE Vector Graphic - Fill","hd":false},{"ty":"tr","p":{"a":0,"k":[74.764,47.668],"ix":2},"a":{"a":0,"k":[0,0],"ix":1},"s":{"a":0,"k":[100,100],"ix":3},"r":{"a":0,"k":0,"ix":6},"o":{"a":0,"k":100,"ix":7},"sk":{"a":0,"k":0,"ix":4},"sa":{"a":0,"k":0,"ix":5},"nm":"Transform"}],"nm":"Group 2","np":2,"cix":2,"bm":0,"ix":2,"mn":"ADBE Vector Group","hd":false}],"ip":0,"op":181,"st":0,"bm":0},{"ddd":0,"ind":4,"ty":4,"nm":"eye black Outlines","sr":1,"ks":{"o":{"a":0,"k":100,"ix":11},"r":{"a":0,"k":0,"ix":10},"p":{"a":1,"k":[{"i":{"x":0.667,"y":1},"o":{"x":0.333,"y":0},"t":41,"s":[371.001,291.976,0],"to":[0,0,0],"ti":[0,0,0]},{"i":{"x":0.667,"y":0.667},"o":{"x":0.333,"y":0.333},"t":60,"s":[425.001,291.976,0],"to":[0,0,0],"ti":[0,0,0]},{"i":{"x":0.667,"y":1},"o":{"x":0.333,"y":0},"t":131,"s":[425.001,291.976,0],"to":[0,0,0],"ti":[0,0,0]},{"t":150,"s":[371.001,291.976,0]}],"ix":2,"l":2},"a":{"a":0,"k":[40.356,57.605,0],"ix":1,"l":2},"s":{"a":0,"k":[100,100,100],"ix":6,"l":2}},"ao":0,"shapes":[{"ty":"gr","it":[{"ind":0,"ty":"sh","ix":1,"ks":{"a":0,"k":{"i":[[22.148,0],[0,-22.149],[0,0],[-22.151,0],[-0.003,22.151],[0,0]],"o":[[-22.151,0],[0,0],[0,22.151],[22.148,0],[0,0],[0,-22.149]],"v":[[0.001,-51.455],[-40.106,-11.35],[-40.106,11.351],[0.001,51.455],[40.106,11.351],[40.106,-11.35]],"c":true},"ix":2},"nm":"Path 1","mn":"ADBE Vector Shape - Group","hd":false},{"ty":"fl","c":{"a":0,"k":[0.117647066303,0.152941176471,0.196078446332,1],"ix":4},"o":{"a":0,"k":100,"ix":5},"r":1,"bm":0,"nm":"Fill 1","mn":"ADBE Vector Graphic - Fill","hd":false},{"ty":"tr","p":{"a":0,"k":[40.356,63.506],"ix":2},"a":{"a":0,"k":[0,0],"ix":1},"s":{"a":0,"k":[100,100],"ix":3},"r":{"a":0,"k":0,"ix":6},"o":{"a":0,"k":100,"ix":7},"sk":{"a":0,"k":0,"ix":4},"sa":{"a":0,"k":0,"ix":5},"nm":"Transform"}],"nm":"Group 1","np":2,"cix":2,"bm":0,"ix":1,"mn":"ADBE Vector Group","hd":false},{"ty":"gr","it":[{"ind":0,"ty":"sh","ix":1,"ks":{"a":0,"k":{"i":[[22.148,0],[0,-22.149],[0,0],[-22.151,0],[-0.003,22.151],[0,0]],"o":[[-22.151,0],[0,0],[0,22.151],[22.148,0],[0,0],[0,-22.149]],"v":[[0.001,-51.455],[-40.106,-11.35],[-40.106,11.351],[0.001,51.455],[40.106,11.351],[40.106,-11.35]],"c":true},"ix":2},"nm":"Path 1","mn":"ADBE Vector Shape - Group","hd":false},{"ty":"fl","c":{"a":0,"k":[0.117647066303,0.152941176471,0.196078446332,1],"ix":4},"o":{"a":0,"k":100,"ix":5},"r":1,"bm":0,"nm":"Fill 1","mn":"ADBE Vector Graphic - Fill","hd":false},{"ty":"tr","p":{"a":0,"k":[40.356,51.705],"ix":2},"a":{"a":0,"k":[0,0],"ix":1},"s":{"a":0,"k":[100,100],"ix":3},"r":{"a":0,"k":0,"ix":6},"o":{"a":0,"k":100,"ix":7},"sk":{"a":0,"k":0,"ix":4},"sa":{"a":0,"k":0,"ix":5},"nm":"Transform"}],"nm":"Group 2","np":2,"cix":2,"bm":0,"ix":2,"mn":"ADBE Vector Group","hd":false}],"ip":0,"op":181,"st":0,"bm":0},{"ddd":0,"ind":5,"ty":4,"nm":"eye white Outlines","sr":1,"ks":{"o":{"a":0,"k":100,"ix":11},"r":{"a":0,"k":0,"ix":10},"p":{"a":0,"k":[396.42,292.3,0],"ix":2,"l":2},"a":{"a":0,"k":[72.949,97.123,0],"ix":1,"l":2},"s":{"a":0,"k":[100,100,100],"ix":6,"l":2}},"ao":0,"shapes":[{"ty":"gr","it":[{"ind":0,"ty":"sh","ix":1,"ks":{"a":0,"k":{"i":[[40.151,0],[0,0],[0,-40.15],[0,0],[-40.151,0],[0,40.15],[0,0]],"o":[[0,0],[-40.151,0],[0,0],[0,40.15],[40.151,0],[0,0],[0,-40.15]],"v":[[0,-90.973],[0,-90.973],[-72.699,-18.274],[-72.699,18.274],[0,90.973],[72.699,18.274],[72.699,-18.274]],"c":true},"ix":2},"nm":"Path 1","mn":"ADBE Vector Shape - Group","hd":false},{"ty":"fl","c":{"a":0,"k":[1,1,1,1],"ix":4},"o":{"a":0,"k":100,"ix":5},"r":1,"bm":0,"nm":"Fill 1","mn":"ADBE Vector Graphic - Fill","hd":false},{"ty":"tr","p":{"a":0,"k":[72.949,103.024],"ix":2},"a":{"a":0,"k":[0,0],"ix":1},"s":{"a":0,"k":[100,100],"ix":3},"r":{"a":0,"k":0,"ix":6},"o":{"a":0,"k":100,"ix":7},"sk":{"a":0,"k":0,"ix":4},"sa":{"a":0,"k":0,"ix":5},"nm":"Transform"}],"nm":"Group 1","np":2,"cix":2,"bm":0,"ix":1,"mn":"ADBE Vector Group","hd":false},{"ty":"gr","it":[{"ind":0,"ty":"sh","ix":1,"ks":{"a":0,"k":{"i":[[40.151,0],[0,0],[0,-40.15],[0,0],[-40.151,0],[0,40.151],[0,0]],"o":[[0,0],[-40.151,0],[0,0],[0,40.151],[40.151,0],[0,0],[0,-40.15]],"v":[[0,-90.973],[0,-90.973],[-72.699,-18.274],[-72.699,18.273],[0,90.973],[72.699,18.273],[72.699,-18.274]],"c":true},"ix":2},"nm":"Path 1","mn":"ADBE Vector Shape - Group","hd":false},{"ty":"fl","c":{"a":0,"k":[1,1,1,1],"ix":4},"o":{"a":0,"k":100,"ix":5},"r":1,"bm":0,"nm":"Fill 1","mn":"ADBE Vector Graphic - Fill","hd":false},{"ty":"tr","p":{"a":0,"k":[72.949,91.223],"ix":2},"a":{"a":0,"k":[0,0],"ix":1},"s":{"a":0,"k":[100,100],"ix":3},"r":{"a":0,"k":0,"ix":6},"o":{"a":0,"k":100,"ix":7},"sk":{"a":0,"k":0,"ix":4},"sa":{"a":0,"k":0,"ix":5},"nm":"Transform"}],"nm":"Group 2","np":2,"cix":2,"bm":0,"ix":2,"mn":"ADBE Vector Group","hd":false}],"ip":0,"op":181,"st":0,"bm":0}]},{"id":"comp_2","nm":"Fly","fr":30,"layers":[{"ddd":0,"ind":1,"ty":4,"nm":"fly Outlines","sr":1,"ks":{"o":{"a":0,"k":100,"ix":11},"r":{"a":0,"k":0,"ix":10},"p":{"a":0,"k":[1196.25,277.594,0],"ix":2,"l":2},"a":{"a":0,"k":[19.774,24.603,0],"ix":1,"l":2},"s":{"a":0,"k":[100,100,100],"ix":6,"l":2}},"ao":0,"shapes":[{"ty":"gr","it":[{"ind":0,"ty":"sh","ix":1,"ks":{"a":0,"k":{"i":[[-6.741,-3.13],[0,0],[3.131,-6.742],[0,0],[6.741,3.13],[-3.131,6.741],[0,0]],"o":[[0,0],[6.741,3.13],[0,0],[-3.131,6.742],[-6.741,-3.131],[0,0],[3.131,-6.741]],"v":[[9.855,-21.223],[9.855,-21.223],[16.393,-3.348],[8.02,14.683],[-9.855,21.222],[-16.393,3.347],[-8.02,-14.685]],"c":true},"ix":2},"nm":"Path 1","mn":"ADBE Vector Shape - Group","hd":false},{"ty":"fl","c":{"a":0,"k":[0.117647066303,0.152941176471,0.196078446332,1],"ix":4},"o":{"a":0,"k":100,"ix":5},"r":1,"bm":0,"nm":"Fill 1","mn":"ADBE Vector Graphic - Fill","hd":false},{"ty":"tr","p":{"a":0,"k":[19.774,24.603],"ix":2},"a":{"a":0,"k":[0,0],"ix":1},"s":{"a":0,"k":[100,100],"ix":3},"r":{"a":0,"k":0,"ix":6},"o":{"a":0,"k":100,"ix":7},"sk":{"a":0,"k":0,"ix":4},"sa":{"a":0,"k":0,"ix":5},"nm":"Transform"}],"nm":"Group 2","np":2,"cix":2,"bm":0,"ix":1,"mn":"ADBE Vector Group","hd":false}],"ip":0,"op":181,"st":0,"bm":0},{"ddd":0,"ind":2,"ty":0,"nm":"Fly wing","parent":1,"refId":"comp_3","sr":1,"ks":{"o":{"a":0,"k":100,"ix":11},"r":{"a":0,"k":0,"ix":10},"p":{"a":0,"k":[19.432,20.655,0],"ix":2,"l":2},"a":{"a":0,"k":[1185.503,291.584,0],"ix":1,"l":2},"s":{"a":0,"k":[-100,-100,100],"ix":6,"l":2}},"ao":0,"w":1489,"h":1080,"ip":0,"op":210,"st":0,"bm":0},{"ddd":0,"ind":3,"ty":0,"nm":"Fly wing","parent":1,"refId":"comp_3","sr":1,"ks":{"o":{"a":0,"k":100,"ix":11},"r":{"a":0,"k":0,"ix":10},"p":{"a":0,"k":[28.432,25.655,0],"ix":2,"l":2},"a":{"a":0,"k":[1185.503,291.584,0],"ix":1,"l":2},"s":{"a":0,"k":[100,100,100],"ix":6,"l":2}},"ao":0,"w":1489,"h":1080,"ip":0,"op":210,"st":0,"bm":0}]},{"id":"comp_3","nm":"Fly wing","fr":30,"layers":[{"ddd":0,"ind":1,"ty":4,"nm":"fly wing Outlines 2","sr":1,"ks":{"o":{"a":0,"k":100,"ix":11},"r":{"a":1,"k":[{"i":{"x":[0.833],"y":[0.833]},"o":{"x":[0.167],"y":[0.167]},"t":0,"s":[41]},{"i":{"x":[0.833],"y":[0.833]},"o":{"x":[0.167],"y":[0.167]},"t":5,"s":[13]},{"t":10,"s":[41]}],"ix":10,"x":"var $bm_rt;\n$bm_rt = loopOut();"},"p":{"a":0,"k":[1188.218,293.006,0],"ix":2,"l":2},"a":{"a":0,"k":[16.666,34.976,0],"ix":1,"l":2},"s":{"a":0,"k":[100,-100,100],"ix":6,"l":2}},"ao":0,"shapes":[{"ty":"gr","it":[{"ind":0,"ty":"sh","ix":1,"ks":{"a":0,"k":{"i":[[-2.092,-8.428],[0,0],[8.428,-2.092],[0,0],[2.092,8.428],[0,0],[-8.428,2.092],[0,0]],"o":[[0,0],[2.092,8.428],[0,0],[-8.428,2.092],[0,0],[-2.092,-8.428],[0,0],[8.428,-2.092]],"v":[[26.533,-6.585],[26.533,-6.585],[15.06,12.463],[-7.484,18.058],[-26.532,6.586],[-26.532,6.585],[-15.059,-12.463],[7.484,-18.058]],"c":true},"ix":2},"nm":"Path 1","mn":"ADBE Vector Shape - Group","hd":false},{"ty":"fl","c":{"a":0,"k":[0.701960784314,0.835294177485,1,1],"ix":4},"o":{"a":0,"k":100,"ix":5},"r":1,"bm":0,"nm":"Fill 1","mn":"ADBE Vector Graphic - Fill","hd":false},{"ty":"tr","p":{"a":0,"k":[28.874,32.201],"ix":2},"a":{"a":0,"k":[0,0],"ix":1},"s":{"a":0,"k":[100,100],"ix":3},"r":{"a":0,"k":0,"ix":6},"o":{"a":0,"k":100,"ix":7},"sk":{"a":0,"k":0,"ix":4},"sa":{"a":0,"k":0,"ix":5},"nm":"Transform"}],"nm":"Group 1","np":2,"cix":2,"bm":0,"ix":1,"mn":"ADBE Vector Group","hd":false}],"ip":0,"op":181,"st":0,"bm":0},{"ddd":0,"ind":2,"ty":4,"nm":"fly wing Outlines","sr":1,"ks":{"o":{"a":0,"k":100,"ix":11},"r":{"a":1,"k":[{"i":{"x":[0.833],"y":[0.833]},"o":{"x":[0.167],"y":[0.167]},"t":0,"s":[0]},{"i":{"x":[0.833],"y":[0.833]},"o":{"x":[0.167],"y":[0.167]},"t":5,"s":[33]},{"t":10,"s":[0]}],"ix":10,"x":"var $bm_rt;\n$bm_rt = loopOut();"},"p":{"a":0,"k":[1188.218,293.006,0],"ix":2,"l":2},"a":{"a":0,"k":[16.666,34.976,0],"ix":1,"l":2},"s":{"a":0,"k":[100,100,100],"ix":6,"l":2}},"ao":0,"shapes":[{"ty":"gr","it":[{"ind":0,"ty":"sh","ix":1,"ks":{"a":0,"k":{"i":[[-2.092,-8.428],[0,0],[8.428,-2.092],[0,0],[2.092,8.428],[0,0],[-8.428,2.092],[0,0]],"o":[[0,0],[2.092,8.428],[0,0],[-8.428,2.092],[0,0],[-2.092,-8.428],[0,0],[8.428,-2.092]],"v":[[26.533,-6.585],[26.533,-6.585],[15.06,12.463],[-7.484,18.058],[-26.532,6.586],[-26.532,6.585],[-15.059,-12.463],[7.484,-18.058]],"c":true},"ix":2},"nm":"Path 1","mn":"ADBE Vector Shape - Group","hd":false},{"ty":"fl","c":{"a":0,"k":[0.701960784314,0.835294177485,1,1],"ix":4},"o":{"a":0,"k":100,"ix":5},"r":1,"bm":0,"nm":"Fill 1","mn":"ADBE Vector Graphic - Fill","hd":false},{"ty":"tr","p":{"a":0,"k":[28.874,32.201],"ix":2},"a":{"a":0,"k":[0,0],"ix":1},"s":{"a":0,"k":[100,100],"ix":3},"r":{"a":0,"k":0,"ix":6},"o":{"a":0,"k":100,"ix":7},"sk":{"a":0,"k":0,"ix":4},"sa":{"a":0,"k":0,"ix":5},"nm":"Transform"}],"nm":"Group 1","np":2,"cix":2,"bm":0,"ix":1,"mn":"ADBE Vector Group","hd":false}],"ip":0,"op":181,"st":0,"bm":0}]}],"layers":[{"ddd":0,"ind":1,"ty":0,"nm":"Tingu in litter box","refId":"comp_0","sr":1,"ks":{"o":{"a":0,"k":100,"ix":11},"r":{"a":0,"k":0,"ix":10},"p":{"a":0,"k":[744,540,0],"ix":2,"l":2},"a":{"a":0,"k":[744.5,540,0],"ix":1,"l":2},"s":{"a":0,"k":[100,100,100],"ix":6,"l":2}},"ao":0,"w":1489,"h":1080,"ip":0,"op":181,"st":0,"bm":0}],"markers":[]}